<?xml version="1.0" encoding="UTF-8"?>
<root t='150' id='1' V150='13' creationTimestamp='0x16e4669a430' V1='4' name='E2BPMEPOCOND002' incarnation='207'>
  <rootElem t='167' id='2' V167='21' V283='2' occurMaxTimes='1' minSize='-1' maxSize='-1' groupType='1' repHandlerStruct='' visible='true' inheritsFrom='' V281='13' V1='4' name='E2BPMEPOCOND002' description='Conditions in Purchase Order'>
    <structNode t='150' idref='1'/>
    <delimTerminator>\n</delimTerminator>
    <child t='167' id='3' V167='21' V283='2' occurMinTimes='1' occurMaxTimes='1' minSize='30' maxSize='30' dataType='2' repHandlerStruct='' visible='true' inheritsFrom='' delimIncludeInitiator='true' V281='13' V1='4' name='SEGNAM' description='Segment name'>
      <structNode t='150' idref='1'/>
      <delimInitiator>E2BPMEPOCOND002               </delimInitiator>
    </child>
    <child t='167' id='4' V167='21' V283='2' occurMinTimes='1' occurMaxTimes='1' minSize='3' maxSize='3' dataType='2' repHandlerStruct='' visible='true' inheritsFrom='' V281='13' V1='4' name='MANDT' description='Client'>
      <structNode t='150' idref='1'/>
    </child>
    <child t='167' id='5' V167='21' V283='2' occurMinTimes='1' occurMaxTimes='1' minSize='16' maxSize='16' dataType='2' repHandlerStruct='' visible='true' inheritsFrom='' V281='13' V1='4' name='DOCNUM' description='Number'>
      <structNode t='150' idref='1'/>
    </child>
    <child t='167' id='6' V167='21' V283='2' occurMinTimes='1' occurMaxTimes='1' minSize='6' maxSize='6' dataType='2' repHandlerStruct='' visible='true' inheritsFrom='' V281='13' V1='4' name='SEGNUM' description='Record number'>
      <structNode t='150' idref='1'/>
    </child>
    <child t='167' id='7' V167='21' V283='2' occurMinTimes='1' occurMaxTimes='1' minSize='6' maxSize='6' dataType='2' repHandlerStruct='' visible='true' inheritsFrom='' V281='13' V1='4' name='PSGNUM' description='Parent record number'>
      <structNode t='150' idref='1'/>
    </child>
    <child t='167' id='8' V167='21' V283='2' occurMinTimes='1' occurMaxTimes='1' minSize='2' maxSize='2' dataType='2' repHandlerStruct='' visible='true' inheritsFrom='' V281='13' V1='4' name='HLEVEL' description='Hierarchy level'>
      <structNode t='150' idref='1'/>
    </child>
    <child t='167' id='9' V167='21' V283='2' occurMaxTimes='1' minSize='10' maxSize='10' dataType='2' repHandlerStruct='' visible='true' inheritsFrom='' V281='13' V1='4' name='CONDITION_NO' description='Number of the Document Condition'>
      <structNode t='150' idref='1'/>
    </child>
    <child t='167' id='10' V167='21' V283='2' occurMaxTimes='1' minSize='6' maxSize='6' dataType='12' dataFormat='213' repHandlerStruct='' visible='true' inheritsFrom='' V281='13' V1='4' name='ITM_NUMBER' description='Condition item number'>
      <structNode t='150' idref='1'/>
    </child>
    <child t='167' id='11' V167='21' V283='2' occurMaxTimes='1' minSize='3' maxSize='3' dataType='12' dataFormat='213' repHandlerStruct='' visible='true' inheritsFrom='' V281='13' V1='4' name='COND_ST_NO' description='Step Number'>
      <structNode t='150' idref='1'/>
    </child>
    <child t='167' id='12' V167='21' V283='2' occurMaxTimes='1' minSize='2' maxSize='2' dataType='11' dataFormat='213' repHandlerStruct='' visible='true' inheritsFrom='' V281='13' V1='4' name='COND_COUNT' description='Condition counter (short length)'>
      <structNode t='150' idref='1'/>
    </child>
    <child t='167' id='13' V167='21' V283='2' occurMaxTimes='1' minSize='4' maxSize='4' dataType='2' repHandlerStruct='' visible='true' inheritsFrom='' V281='13' V1='4' name='COND_TYPE' description='Condition type'>
      <structNode t='150' idref='1'/>
    </child>
    <child t='167' id='14' V167='21' V283='2' occurMaxTimes='1' minSize='31' maxSize='31' dataType='22' dataFormat='212' repHandlerStruct='' visible='true' inheritsFrom='' V281='13' V1='4' name='COND_VALUE' description='Condition Amount'>
      <structNode t='150' idref='1'/>
    </child>
    <child t='167' id='15' V167='21' V283='2' occurMaxTimes='1' minSize='5' maxSize='5' dataType='2' repHandlerStruct='' visible='true' inheritsFrom='' V281='13' V1='4' name='CURRENCY' description='Currency Key'>
      <structNode t='150' idref='1'/>
    </child>
    <child t='167' id='16' V167='21' V283='2' occurMaxTimes='1' minSize='3' maxSize='3' dataType='2' repHandlerStruct='' visible='true' inheritsFrom='' V281='13' V1='4' name='CURRENCY_ISO' description='ISO code currency'>
      <structNode t='150' idref='1'/>
    </child>
    <child t='167' id='17' V167='21' V283='2' occurMaxTimes='1' minSize='3' maxSize='3' dataType='2' repHandlerStruct='' visible='true' inheritsFrom='' V281='13' V1='4' name='COND_UNIT' description='Condition Unit'>
      <structNode t='150' idref='1'/>
    </child>
    <child t='167' id='18' V167='21' V283='2' occurMaxTimes='1' minSize='3' maxSize='3' dataType='2' repHandlerStruct='' visible='true' inheritsFrom='' V281='13' V1='4' name='COND_UNIT_ISO' description='Condition unit of measure in UoM'>
      <structNode t='150' idref='1'/>
    </child>
    <child t='167' id='19' V167='21' V283='2' occurMaxTimes='1' minSize='6' maxSize='6' dataType='22' dataFormat='212' repHandlerStruct='' visible='true' inheritsFrom='' V281='13' V1='4' name='COND_P_UNT' description='Condition Pricing Unit'>
      <structNode t='150' idref='1'/>
    </child>
    <child t='167' id='20' V167='21' V283='2' occurMaxTimes='1' minSize='2' maxSize='2' dataType='2' repHandlerStruct='' visible='true' inheritsFrom='' V281='13' V1='4' name='APPLICATIO' description='Application'>
      <structNode t='150' idref='1'/>
    </child>
    <child t='167' id='21' V167='21' V283='2' occurMaxTimes='1' minSize='8' maxSize='8' dataType='31' dataFormat='301' repHandlerStruct='' visible='true' inheritsFrom='' V281='13' V1='4' name='CONPRICDAT' description='Condition pricing date'>
      <structNode t='150' idref='1'/>
    </child>
    <child t='167' id='22' V167='21' V283='2' occurMaxTimes='1' minSize='1' maxSize='1' dataType='2' repHandlerStruct='' visible='true' inheritsFrom='' V281='13' V1='4' name='CALCTYPCON' description='Calculation Type for Condition' checksumValid='true' checksum='Tbuiv4Kc4b0Fk7ZvNG6eYiDNk98='>
      <structNode t='150' idref='1'/>
      <child t='167' id='23' V167='21' V283='2' occurMaxTimes='1' minSize='-1' maxSize='-1' dataType='2' elemType='5' repHandlerStruct='' visible='true' inheritsFrom='' V281='13' V1='4' name='A' description='Percentage'>
        <structNode t='150' idref='1'/>
      </child>
      <child t='167' id='24' V167='21' V283='2' occurMaxTimes='1' minSize='-1' maxSize='-1' dataType='2' elemType='5' repHandlerStruct='' visible='true' inheritsFrom='' V281='13' V1='4' name='B' description='Fixed amount'>
        <structNode t='150' idref='1'/>
      </child>
      <child t='167' id='25' V167='21' V283='2' occurMaxTimes='1' minSize='-1' maxSize='-1' dataType='2' elemType='5' repHandlerStruct='' visible='true' inheritsFrom='' V281='13' V1='4' name='C' description='Quantity'>
        <structNode t='150' idref='1'/>
      </child>
      <child t='167' id='26' V167='21' V283='2' occurMaxTimes='1' minSize='-1' maxSize='-1' dataType='2' elemType='5' repHandlerStruct='' visible='true' inheritsFrom='' V281='13' V1='4' name='D' description='Gross weight'>
        <structNode t='150' idref='1'/>
      </child>
      <child t='167' id='27' V167='21' V283='2' occurMaxTimes='1' minSize='-1' maxSize='-1' dataType='2' elemType='5' repHandlerStruct='' visible='true' inheritsFrom='' V281='13' V1='4' name='E' description='Net weight'>
        <structNode t='150' idref='1'/>
      </child>
      <child t='167' id='28' V167='21' V283='2' occurMaxTimes='1' minSize='-1' maxSize='-1' dataType='2' elemType='5' repHandlerStruct='' visible='true' inheritsFrom='' V281='13' V1='4' name='F' description='Volume'>
        <structNode t='150' idref='1'/>
      </child>
      <child t='167' id='29' V167='21' V283='2' occurMaxTimes='1' minSize='-1' maxSize='-1' dataType='2' elemType='5' repHandlerStruct='' visible='true' inheritsFrom='' V281='13' V1='4' name='G' description='Formula'>
        <structNode t='150' idref='1'/>
      </child>
      <child t='167' id='30' V167='21' V283='2' occurMaxTimes='1' minSize='-1' maxSize='-1' dataType='2' elemType='5' repHandlerStruct='' visible='true' inheritsFrom='' V281='13' V1='4' name='H' description='Percentage (in Hundreds)'>
        <structNode t='150' idref='1'/>
      </child>
      <child t='167' id='31' V167='21' V283='2' occurMaxTimes='1' minSize='-1' maxSize='-1' dataType='2' elemType='5' repHandlerStruct='' visible='true' inheritsFrom='' V281='13' V1='4' name='I' description='Percentage (Travel Costs)'>
        <structNode t='150' idref='1'/>
      </child>
      <child t='167' id='32' V167='21' V283='2' occurMaxTimes='1' minSize='-1' maxSize='-1' dataType='2' elemType='5' repHandlerStruct='' visible='true' inheritsFrom='' V281='13' V1='4' name='K' description='Per mille (in Thousands)'>
        <structNode t='150' idref='1'/>
      </child>
      <child t='167' id='33' V167='21' V283='2' occurMaxTimes='1' minSize='-1' maxSize='-1' dataType='2' elemType='5' repHandlerStruct='' visible='true' inheritsFrom='' V281='13' V1='4' name='J' description='Per mille'>
        <structNode t='150' idref='1'/>
      </child>
      <child t='167' id='34' V167='21' V283='2' occurMaxTimes='1' minSize='-1' maxSize='-1' dataType='2' elemType='5' repHandlerStruct='' visible='true' inheritsFrom='' V281='13' V1='4' name='L' description='Points'>
        <structNode t='150' idref='1'/>
      </child>
      <child t='167' id='35' V167='21' V283='2' occurMaxTimes='1' minSize='-1' maxSize='-1' dataType='2' elemType='5' repHandlerStruct='' visible='true' inheritsFrom='' V281='13' V1='4' name='M' description='Quantity - Monthly Price'>
        <structNode t='150' idref='1'/>
      </child>
      <child t='167' id='36' V167='21' V283='2' occurMaxTimes='1' minSize='-1' maxSize='-1' dataType='2' elemType='5' repHandlerStruct='' visible='true' inheritsFrom='' V281='13' V1='4' name='N' description='Quantity - Year Price'>
        <structNode t='150' idref='1'/>
      </child>
      <child t='167' id='37' V167='21' V283='2' occurMaxTimes='1' minSize='-1' maxSize='-1' dataType='2' elemType='5' repHandlerStruct='' visible='true' inheritsFrom='' V281='13' V1='4' name='O' description='Quantity - Daily Price'>
        <structNode t='150' idref='1'/>
      </child>
      <child t='167' id='38' V167='21' V283='2' occurMaxTimes='1' minSize='-1' maxSize='-1' dataType='2' elemType='5' repHandlerStruct='' visible='true' inheritsFrom='' V281='13' V1='4' name='P' description='Quantity - Weekly Price'>
        <structNode t='150' idref='1'/>
      </child>
      <child t='167' id='39' V167='21' V283='2' occurMaxTimes='1' minSize='-1' maxSize='-1' dataType='2' elemType='5' repHandlerStruct='' visible='true' inheritsFrom='' V281='13' V1='4' name='Q' description='Commodity Price'>
        <structNode t='150' idref='1'/>
      </child>
      <child t='167' id='40' V167='21' V283='2' occurMaxTimes='1' minSize='-1' maxSize='-1' dataType='2' elemType='5' repHandlerStruct='' visible='true' inheritsFrom='' V281='13' V1='4' name='R' description='Distance-dependent'>
        <structNode t='150' idref='1'/>
      </child>
      <child t='167' id='41' V167='21' V283='2' occurMaxTimes='1' minSize='-1' maxSize='-1' dataType='2' elemType='5' repHandlerStruct='' visible='true' inheritsFrom='' V281='13' V1='4' name='S' description='Number of shipping units'>
        <structNode t='150' idref='1'/>
      </child>
      <child t='167' id='42' V167='21' V283='2' occurMaxTimes='1' minSize='-1' maxSize='-1' dataType='2' elemType='5' repHandlerStruct='' visible='true' inheritsFrom='' V281='13' V1='4' name='T' description='Multi-dimensional'>
        <structNode t='150' idref='1'/>
      </child>
      <child t='167' id='43' V167='21' V283='2' occurMaxTimes='1' minSize='-1' maxSize='-1' dataType='2' elemType='5' repHandlerStruct='' visible='true' inheritsFrom='' V281='13' V1='4' name='U' description='Percentage FIN (CRM Only)'>
        <structNode t='150' idref='1'/>
      </child>
      <child t='167' id='44' V167='21' V283='2' occurMaxTimes='1' minSize='-1' maxSize='-1' dataType='2' elemType='5' repHandlerStruct='' visible='true' inheritsFrom='' V281='13' V1='4' name='V' description='Quantity Adjustment'>
        <structNode t='150' idref='1'/>
      </child>
      <child t='167' id='45' V167='21' V283='2' occurMaxTimes='1' minSize='-1' maxSize='-1' dataType='2' elemType='5' repHandlerStruct='' visible='true' inheritsFrom='' V281='13' V1='4' name='W' description='Percentage (with 6 Decimal Places)'>
        <structNode t='150' idref='1'/>
      </child>
    </child>
    <child t='167' id='46' V167='21' V283='2' occurMaxTimes='1' minSize='31' maxSize='31' dataType='22' dataFormat='212' repHandlerStruct='' visible='true' inheritsFrom='' V281='13' V1='4' name='CONBASEVAL' description='Condition base value'>
      <structNode t='150' idref='1'/>
    </child>
    <child t='167' id='47' V167='21' V283='2' occurMaxTimes='1' minSize='11' maxSize='11' dataType='22' dataFormat='212' repHandlerStruct='' visible='true' inheritsFrom='' V281='13' V1='4' name='CONEXCHRAT' description='Condition exchange rate for conversion to local currency'>
      <structNode t='150' idref='1'/>
    </child>
    <child t='167' id='48' V167='21' V283='2' occurMaxTimes='1' minSize='6' maxSize='6' dataType='22' dataFormat='212' repHandlerStruct='' visible='true' inheritsFrom='' V281='13' V1='4' name='NUMCONVERT' description='Numerator for converting condition units to base units'>
      <structNode t='150' idref='1'/>
    </child>
    <child t='167' id='49' V167='21' V283='2' occurMaxTimes='1' minSize='6' maxSize='6' dataType='22' dataFormat='212' repHandlerStruct='' visible='true' inheritsFrom='' V281='13' V1='4' name='DENOMINATO' description='Denominator for converting condition units to base units'>
      <structNode t='150' idref='1'/>
    </child>
    <child t='167' id='50' V167='21' V283='2' occurMaxTimes='1' minSize='1' maxSize='1' dataType='2' repHandlerStruct='' visible='true' inheritsFrom='' V281='13' V1='4' name='CONDTYPE' description='Condition Category (Examples: Tax, Freight, Price, Cost)' checksumValid='true' checksum='eIiqFHxp2CTpiDFOoHgmCJCMKVk='>
      <structNode t='150' idref='1'/>
      <child t='167' id='51' V167='21' V283='2' occurMaxTimes='1' minSize='-1' maxSize='-1' dataType='2' elemType='5' repHandlerStruct='' visible='true' inheritsFrom='' V281='13' V1='4' name='$' description='TaxJurCode trigger  (without license check KNVL)'>
        <structNode t='150' idref='1'/>
      </child>
      <child t='167' id='52' V167='21' V283='2' occurMaxTimes='1' minSize='-1' maxSize='-1' dataType='2' elemType='5' repHandlerStruct='' visible='true' inheritsFrom='' V281='13' V1='4' name='+' description='Tax exemption license via conditions'>
        <structNode t='150' idref='1'/>
      </child>
      <child t='167' id='53' V167='21' V283='2' occurMaxTimes='1' minSize='-1' maxSize='-1' dataType='2' elemType='5' repHandlerStruct='' visible='true' inheritsFrom='' V281='13' V1='4' name='-' description='Total charges (only IS-OIL)'>
        <structNode t='150' idref='1'/>
      </child>
      <child t='167' id='54' V167='21' V283='2' occurMaxTimes='1' minSize='-1' maxSize='-1' dataType='2' elemType='5' repHandlerStruct='' visible='true' inheritsFrom='' V281='13' V1='4' name='0' description=' Charges - condition records (only IS-OIL)'>
        <structNode t='150' idref='1'/>
      </child>
      <child t='167' id='55' V167='21' V283='2' occurMaxTimes='1' minSize='-1' maxSize='-1' dataType='2' elemType='5' repHandlerStruct='' visible='true' inheritsFrom='' V281='13' V1='4' name='1' description='Tax JurDic level 1 (with license check KNVL)'>
        <structNode t='150' idref='1'/>
      </child>
      <child t='167' id='56' V167='21' V283='2' occurMaxTimes='1' minSize='-1' maxSize='-1' dataType='2' elemType='5' repHandlerStruct='' visible='true' inheritsFrom='' V281='13' V1='4' name='2' description='Tax JurDic level 2'>
        <structNode t='150' idref='1'/>
      </child>
      <child t='167' id='57' V167='21' V283='2' occurMaxTimes='1' minSize='-1' maxSize='-1' dataType='2' elemType='5' repHandlerStruct='' visible='true' inheritsFrom='' V281='13' V1='4' name='3' description='Tax JurDic level 3'>
        <structNode t='150' idref='1'/>
      </child>
      <child t='167' id='58' V167='21' V283='2' occurMaxTimes='1' minSize='-1' maxSize='-1' dataType='2' elemType='5' repHandlerStruct='' visible='true' inheritsFrom='' V281='13' V1='4' name='4' description='Tax JurDic level 4'>
        <structNode t='150' idref='1'/>
      </child>
      <child t='167' id='59' V167='21' V283='2' occurMaxTimes='1' minSize='-1' maxSize='-1' dataType='2' elemType='5' repHandlerStruct='' visible='true' inheritsFrom='' V281='13' V1='4' name='5' description='Customer reserve 5'>
        <structNode t='150' idref='1'/>
      </child>
      <child t='167' id='60' V167='21' V283='2' occurMaxTimes='1' minSize='-1' maxSize='-1' dataType='2' elemType='5' repHandlerStruct='' visible='true' inheritsFrom='' V281='13' V1='4' name='6' description='Customer reserve 6'>
        <structNode t='150' idref='1'/>
      </child>
      <child t='167' id='61' V167='21' V283='2' occurMaxTimes='1' minSize='-1' maxSize='-1' dataType='2' elemType='5' repHandlerStruct='' visible='true' inheritsFrom='' V281='13' V1='4' name='7' description='Customer reserve 7'>
        <structNode t='150' idref='1'/>
      </child>
      <child t='167' id='62' V167='21' V283='2' occurMaxTimes='1' minSize='-1' maxSize='-1' dataType='2' elemType='5' repHandlerStruct='' visible='true' inheritsFrom='' V281='13' V1='4' name='8' description='Customer reserve 8'>
        <structNode t='150' idref='1'/>
      </child>
      <child t='167' id='63' V167='21' V283='2' occurMaxTimes='1' minSize='-1' maxSize='-1' dataType='2' elemType='5' repHandlerStruct='' visible='true' inheritsFrom='' V281='13' V1='4' name='9' description='Customer reserve 9'>
        <structNode t='150' idref='1'/>
      </child>
      <child t='167' id='64' V167='21' V283='2' occurMaxTimes='1' minSize='-1' maxSize='-1' dataType='2' elemType='5' repHandlerStruct='' visible='true' inheritsFrom='' V281='13' V1='4' name='A' description='Packaging'>
        <structNode t='150' idref='1'/>
      </child>
      <child t='167' id='65' V167='21' V283='2' occurMaxTimes='1' minSize='-1' maxSize='-1' dataType='2' elemType='5' repHandlerStruct='' visible='true' inheritsFrom='' V281='13' V1='4' name='B' description='Delivery costs'>
        <structNode t='150' idref='1'/>
      </child>
      <child t='167' id='66' V167='21' V283='2' occurMaxTimes='1' minSize='-1' maxSize='-1' dataType='2' elemType='5' repHandlerStruct='' visible='true' inheritsFrom='' V281='13' V1='4' name='C' description='Insurance'>
        <structNode t='150' idref='1'/>
      </child>
      <child t='167' id='67' V167='21' V283='2' occurMaxTimes='1' minSize='-1' maxSize='-1' dataType='2' elemType='5' repHandlerStruct='' visible='true' inheritsFrom='' V281='13' V1='4' name='D' description='Tax'>
        <structNode t='150' idref='1'/>
      </child>
      <child t='167' id='68' V167='21' V283='2' occurMaxTimes='1' minSize='-1' maxSize='-1' dataType='2' elemType='5' repHandlerStruct='' visible='true' inheritsFrom='' V281='13' V1='4' name='E' description='Cash discount'>
        <structNode t='150' idref='1'/>
      </child>
      <child t='167' id='69' V167='21' V283='2' occurMaxTimes='1' minSize='-1' maxSize='-1' dataType='2' elemType='5' repHandlerStruct='' visible='true' inheritsFrom='' V281='13' V1='4' name='F' description='Freight'>
        <structNode t='150' idref='1'/>
      </child>
      <child t='167' id='70' V167='21' V283='2' occurMaxTimes='1' minSize='-1' maxSize='-1' dataType='2' elemType='5' repHandlerStruct='' visible='true' inheritsFrom='' V281='13' V1='4' name='G' description='Internal price'>
        <structNode t='150' idref='1'/>
      </child>
      <child t='167' id='71' V167='21' V283='2' occurMaxTimes='1' minSize='-1' maxSize='-1' dataType='2' elemType='5' repHandlerStruct='' visible='true' inheritsFrom='' V281='13' V1='4' name='H' description='Basic price'>
        <structNode t='150' idref='1'/>
      </child>
      <child t='167' id='72' V167='21' V283='2' occurMaxTimes='1' minSize='-1' maxSize='-1' dataType='2' elemType='5' repHandlerStruct='' visible='true' inheritsFrom='' V281='13' V1='4' name='I' description='Price for intercompany billing'>
        <structNode t='150' idref='1'/>
      </child>
      <child t='167' id='73' V167='21' V283='2' occurMaxTimes='1' minSize='-1' maxSize='-1' dataType='2' elemType='5' repHandlerStruct='' visible='true' inheritsFrom='' V281='13' V1='4' name='J' description='Customer expected price / customer value (excl.tax)'>
        <structNode t='150' idref='1'/>
      </child>
      <child t='167' id='74' V167='21' V283='2' occurMaxTimes='1' minSize='-1' maxSize='-1' dataType='2' elemType='5' repHandlerStruct='' visible='true' inheritsFrom='' V281='13' V1='4' name='K' description='Base amount excluding tax'>
        <structNode t='150' idref='1'/>
      </child>
      <child t='167' id='75' V167='21' V283='2' occurMaxTimes='1' minSize='-1' maxSize='-1' dataType='2' elemType='5' repHandlerStruct='' visible='true' inheritsFrom='' V281='13' V1='4' name='L' description='Generally new when copying'>
        <structNode t='150' idref='1'/>
      </child>
      <child t='167' id='76' V167='21' V283='2' occurMaxTimes='1' minSize='-1' maxSize='-1' dataType='2' elemType='5' repHandlerStruct='' visible='true' inheritsFrom='' V281='13' V1='4' name='M' description='Sales tax w/license-checking (VAT)'>
        <structNode t='150' idref='1'/>
      </child>
      <child t='167' id='77' V167='21' V283='2' occurMaxTimes='1' minSize='-1' maxSize='-1' dataType='2' elemType='5' repHandlerStruct='' visible='true' inheritsFrom='' V281='13' V1='4' name='N' description='Input Tax not Deductible'>
        <structNode t='150' idref='1'/>
      </child>
      <child t='167' id='78' V167='21' V283='2' occurMaxTimes='1' minSize='-1' maxSize='-1' dataType='2' elemType='5' repHandlerStruct='' visible='true' inheritsFrom='' V281='13' V1='4' name='O' description='Variants'>
        <structNode t='150' idref='1'/>
      </child>
      <child t='167' id='79' V167='21' V283='2' occurMaxTimes='1' minSize='-1' maxSize='-1' dataType='2' elemType='5' repHandlerStruct='' visible='true' inheritsFrom='' V281='13' V1='4' name='P' description='Base amount including tax'>
        <structNode t='150' idref='1'/>
      </child>
      <child t='167' id='80' V167='21' V283='2' occurMaxTimes='1' minSize='-1' maxSize='-1' dataType='2' elemType='5' repHandlerStruct='' visible='true' inheritsFrom='' V281='13' V1='4' name='Q' description='Costing'>
        <structNode t='150' idref='1'/>
      </child>
      <child t='167' id='81' V167='21' V283='2' occurMaxTimes='1' minSize='-1' maxSize='-1' dataType='2' elemType='5' repHandlerStruct='' visible='true' inheritsFrom='' V281='13' V1='4' name='R' description='Invoice list condition'>
        <structNode t='150' idref='1'/>
      </child>
      <child t='167' id='82' V167='21' V283='2' occurMaxTimes='1' minSize='-1' maxSize='-1' dataType='2' elemType='5' repHandlerStruct='' visible='true' inheritsFrom='' V281='13' V1='4' name='S' description='Standard cost'>
        <structNode t='150' idref='1'/>
      </child>
      <child t='167' id='83' V167='21' V283='2' occurMaxTimes='1' minSize='-1' maxSize='-1' dataType='2' elemType='5' repHandlerStruct='' visible='true' inheritsFrom='' V281='13' V1='4' name='T' description='Moving cost'>
        <structNode t='150' idref='1'/>
      </child>
      <child t='167' id='84' V167='21' V283='2' occurMaxTimes='1' minSize='-1' maxSize='-1' dataType='2' elemType='5' repHandlerStruct='' visible='true' inheritsFrom='' V281='13' V1='4' name='U' description='Discount/surcharge for precious metals'>
        <structNode t='150' idref='1'/>
      </child>
      <child t='167' id='85' V167='21' V283='2' occurMaxTimes='1' minSize='-1' maxSize='-1' dataType='2' elemType='5' repHandlerStruct='' visible='true' inheritsFrom='' V281='13' V1='4' name='V' description='Price component'>
        <structNode t='150' idref='1'/>
      </child>
      <child t='167' id='86' V167='21' V283='2' occurMaxTimes='1' minSize='-1' maxSize='-1' dataType='2' elemType='5' repHandlerStruct='' visible='true' inheritsFrom='' V281='13' V1='4' name='W' description='Expected sales price (including tax)'>
        <structNode t='150' idref='1'/>
      </child>
      <child t='167' id='87' V167='21' V283='2' occurMaxTimes='1' minSize='-1' maxSize='-1' dataType='2' elemType='5' repHandlerStruct='' visible='true' inheritsFrom='' V281='13' V1='4' name='X' description='Customer reserve X'>
        <structNode t='150' idref='1'/>
      </child>
      <child t='167' id='88' V167='21' V283='2' occurMaxTimes='1' minSize='-1' maxSize='-1' dataType='2' elemType='5' repHandlerStruct='' visible='true' inheritsFrom='' V281='13' V1='4' name='Y' description='Customer reserve Y'>
        <structNode t='150' idref='1'/>
      </child>
      <child t='167' id='89' V167='21' V283='2' occurMaxTimes='1' minSize='-1' maxSize='-1' dataType='2' elemType='5' repHandlerStruct='' visible='true' inheritsFrom='' V281='13' V1='4' name='Z' description='Customer reserve Z'>
        <structNode t='150' idref='1'/>
      </child>
      <child t='167' id='90' V167='21' V283='2' occurMaxTimes='1' minSize='-1' maxSize='-1' dataType='2' elemType='5' repHandlerStruct='' visible='true' inheritsFrom='' V281='13' V1='4' name='a' description='Reserved (fixed extra pay)'>
        <structNode t='150' idref='1'/>
      </child>
      <child t='167' id='91' V167='21' V283='2' occurMaxTimes='1' minSize='-1' maxSize='-1' dataType='2' elemType='5' repHandlerStruct='' visible='true' inheritsFrom='' V281='13' V1='4' name='b' description='Transfer Price for Group Valuation'>
        <structNode t='150' idref='1'/>
      </child>
      <child t='167' id='92' V167='21' V283='2' occurMaxTimes='1' minSize='-1' maxSize='-1' dataType='2' elemType='5' repHandlerStruct='' visible='true' inheritsFrom='' V281='13' V1='4' name='c' description='Transfer price for profit centers'>
        <structNode t='150' idref='1'/>
      </child>
      <child t='167' id='93' V167='21' V283='2' occurMaxTimes='1' minSize='-1' maxSize='-1' dataType='2' elemType='5' repHandlerStruct='' visible='true' inheritsFrom='' V281='13' V1='4' name='d' description='Confirmed purchase net price/value'>
        <structNode t='150' idref='1'/>
      </child>
      <child t='167' id='94' V167='21' V283='2' occurMaxTimes='1' minSize='-1' maxSize='-1' dataType='2' elemType='5' repHandlerStruct='' visible='true' inheritsFrom='' V281='13' V1='4' name='e' description='Down payment request/down payment clearing'>
        <structNode t='150' idref='1'/>
      </child>
      <child t='167' id='95' V167='21' V283='2' occurMaxTimes='1' minSize='-1' maxSize='-1' dataType='2' elemType='5' repHandlerStruct='' visible='true' inheritsFrom='' V281='13' V1='4' name='f' description='Free goods - inclusive'>
        <structNode t='150' idref='1'/>
      </child>
      <child t='167' id='96' V167='21' V283='2' occurMaxTimes='1' minSize='-1' maxSize='-1' dataType='2' elemType='5' repHandlerStruct='' visible='true' inheritsFrom='' V281='13' V1='4' name='g' description='Payment'>
        <structNode t='150' idref='1'/>
      </child>
      <child t='167' id='97' V167='21' V283='2' occurMaxTimes='1' minSize='-1' maxSize='-1' dataType='2' elemType='5' repHandlerStruct='' visible='true' inheritsFrom='' V281='13' V1='4' name='h' description='Profit Center Cost'>
        <structNode t='150' idref='1'/>
      </child>
      <child t='167' id='98' V167='21' V283='2' occurMaxTimes='1' minSize='-1' maxSize='-1' dataType='2' elemType='5' repHandlerStruct='' visible='true' inheritsFrom='' V281='13' V1='4' name='i' description='Ship &amp; Debit 1 (IBU HiTec)'>
        <structNode t='150' idref='1'/>
      </child>
      <child t='167' id='99' V167='21' V283='2' occurMaxTimes='1' minSize='-1' maxSize='-1' dataType='2' elemType='5' repHandlerStruct='' visible='true' inheritsFrom='' V281='13' V1='4' name='j' description='Ship &amp; Debit 2 (IBU HiTec)'>
        <structNode t='150' idref='1'/>
      </child>
      <child t='167' id='100' V167='21' V283='2' occurMaxTimes='1' minSize='-1' maxSize='-1' dataType='2' elemType='5' repHandlerStruct='' visible='true' inheritsFrom='' V281='13' V1='4' name='l' description='TP-ILV: Base Tarif That Covers Costs'>
        <structNode t='150' idref='1'/>
      </child>
      <child t='167' id='101' V167='21' V283='2' occurMaxTimes='1' minSize='-1' maxSize='-1' dataType='2' elemType='5' repHandlerStruct='' visible='true' inheritsFrom='' V281='13' V1='4' name='m' description='SSR Discount (only IS-Oil)'>
        <structNode t='150' idref='1'/>
      </child>
      <child t='167' id='102' V167='21' V283='2' occurMaxTimes='1' minSize='-1' maxSize='-1' dataType='2' elemType='5' repHandlerStruct='' visible='true' inheritsFrom='' V281='13' V1='4' name='n' description='Profit Center Internal Price (Route)'>
        <structNode t='150' idref='1'/>
      </child>
      <child t='167' id='103' V167='21' V283='2' occurMaxTimes='1' minSize='-1' maxSize='-1' dataType='2' elemType='5' repHandlerStruct='' visible='true' inheritsFrom='' V281='13' V1='4' name='o' description='AFS Season Determination'>
        <structNode t='150' idref='1'/>
      </child>
      <child t='167' id='104' V167='21' V283='2' occurMaxTimes='1' minSize='-1' maxSize='-1' dataType='2' elemType='5' repHandlerStruct='' visible='true' inheritsFrom='' V281='13' V1='4' name='p' description='SSR Partner Commission (only IS-OIL)'>
        <structNode t='150' idref='1'/>
      </child>
      <child t='167' id='105' V167='21' V283='2' occurMaxTimes='1' minSize='-1' maxSize='-1' dataType='2' elemType='5' repHandlerStruct='' visible='true' inheritsFrom='' V281='13' V1='4' name='&amp;' description='AFS Value-Added Services'>
        <structNode t='150' idref='1'/>
      </child>
    </child>
    <child t='167' id='106' V167='21' V283='2' occurMaxTimes='1' minSize='1' maxSize='1' dataType='2' repHandlerStruct='' visible='true' inheritsFrom='' V281='13' V1='4' name='STAT_CON' description='Condition is used for statistics'>
      <structNode t='150' idref='1'/>
      <child t='167' id='107' V167='21' V283='2' occurMaxTimes='1' minSize='-1' maxSize='-1' dataType='2' elemType='5' repHandlerStruct='' visible='true' inheritsFrom='' V281='13' V1='4' name='X' description='Yes'>
        <structNode t='150' idref='1'/>
      </child>
    </child>
    <child t='167' id='108' V167='21' V283='2' occurMaxTimes='1' minSize='1' maxSize='1' dataType='2' repHandlerStruct='' visible='true' inheritsFrom='' V281='13' V1='4' name='SCALETYPE' description='Scale Type'>
      <structNode t='150' idref='1'/>
      <child t='167' id='109' V167='21' V283='2' occurMaxTimes='1' minSize='-1' maxSize='-1' dataType='2' elemType='5' repHandlerStruct='' visible='true' inheritsFrom='' V281='13' V1='4' name='A' description='Base-scale'>
        <structNode t='150' idref='1'/>
      </child>
      <child t='167' id='110' V167='21' V283='2' occurMaxTimes='1' minSize='-1' maxSize='-1' dataType='2' elemType='5' repHandlerStruct='' visible='true' inheritsFrom='' V281='13' V1='4' name='B' description='To-scale'>
        <structNode t='150' idref='1'/>
      </child>
      <child t='167' id='111' V167='21' V283='2' occurMaxTimes='1' minSize='-1' maxSize='-1' dataType='2' elemType='5' repHandlerStruct='' visible='true' inheritsFrom='' V281='13' V1='4' name='C' description='Not used'>
        <structNode t='150' idref='1'/>
      </child>
      <child t='167' id='112' V167='21' V283='2' occurMaxTimes='1' minSize='-1' maxSize='-1' dataType='2' elemType='5' repHandlerStruct='' visible='true' inheritsFrom='' V281='13' V1='4' name='D' description='Graduated-to interval scale'>
        <structNode t='150' idref='1'/>
      </child>
    </child>
    <child t='167' id='113' V167='21' V283='2' occurMaxTimes='1' minSize='1' maxSize='1' dataType='2' repHandlerStruct='' visible='true' inheritsFrom='' V281='13' V1='4' name='ACCRUALS' description='Condition is Relevant for Accrual  (e.g. Freight)'>
      <structNode t='150' idref='1'/>
      <child t='167' id='114' V167='21' V283='2' occurMaxTimes='1' minSize='-1' maxSize='-1' dataType='2' elemType='5' repHandlerStruct='' visible='true' inheritsFrom='' V281='13' V1='4' name='X' description='Yes'>
        <structNode t='150' idref='1'/>
      </child>
    </child>
    <child t='167' id='115' V167='21' V283='2' occurMaxTimes='1' minSize='1' maxSize='1' dataType='2' repHandlerStruct='' visible='true' inheritsFrom='' V281='13' V1='4' name='CONINVOLST' description='Condition for Invoice List'>
      <structNode t='150' idref='1'/>
    </child>
    <child t='167' id='116' V167='21' V283='2' occurMaxTimes='1' minSize='1' maxSize='1' dataType='2' repHandlerStruct='' visible='true' inheritsFrom='' V281='13' V1='4' name='CONDORIGIN' description='Origin of the Condition' checksumValid='true' checksum='uk2utdoYoFZq/X7uWLY5wffsnNo='>
      <structNode t='150' idref='1'/>
      <child t='167' id='117' V167='21' V283='2' occurMaxTimes='1' minSize='-1' maxSize='-1' dataType='2' elemType='5' repHandlerStruct='' visible='true' inheritsFrom='' V281='13' V1='4' name='A' description='Automatic pricing'>
        <structNode t='150' idref='1'/>
      </child>
      <child t='167' id='118' V167='21' V283='2' occurMaxTimes='1' minSize='-1' maxSize='-1' dataType='2' elemType='5' repHandlerStruct='' visible='true' inheritsFrom='' V281='13' V1='4' name='B' description='Duplicated from main item'>
        <structNode t='150' idref='1'/>
      </child>
      <child t='167' id='119' V167='21' V283='2' occurMaxTimes='1' minSize='-1' maxSize='-1' dataType='2' elemType='5' repHandlerStruct='' visible='true' inheritsFrom='' V281='13' V1='4' name='C' description='Manually entered'>
        <structNode t='150' idref='1'/>
      </child>
      <child t='167' id='120' V167='21' V283='2' occurMaxTimes='1' minSize='-1' maxSize='-1' dataType='2' elemType='5' repHandlerStruct='' visible='true' inheritsFrom='' V281='13' V1='4' name='D' description='Header condition'>
        <structNode t='150' idref='1'/>
      </child>
      <child t='167' id='121' V167='21' V283='2' occurMaxTimes='1' minSize='-1' maxSize='-1' dataType='2' elemType='5' repHandlerStruct='' visible='true' inheritsFrom='' V281='13' V1='4' name='E' description='Item total'>
        <structNode t='150' idref='1'/>
      </child>
      <child t='167' id='122' V167='21' V283='2' occurMaxTimes='1' minSize='-1' maxSize='-1' dataType='2' elemType='5' repHandlerStruct='' visible='true' inheritsFrom='' V281='13' V1='4' name='F' description='Condition supplement'>
        <structNode t='150' idref='1'/>
      </child>
      <child t='167' id='123' V167='21' V283='2' occurMaxTimes='1' minSize='-1' maxSize='-1' dataType='2' elemType='5' repHandlerStruct='' visible='true' inheritsFrom='' V281='13' V1='4' name='G' description='Original header condition'>
        <structNode t='150' idref='1'/>
      </child>
      <child t='167' id='124' V167='21' V283='2' occurMaxTimes='1' minSize='-1' maxSize='-1' dataType='2' elemType='5' repHandlerStruct='' visible='true' inheritsFrom='' V281='13' V1='4' name='H' description='Correction Rebate'>
        <structNode t='150' idref='1'/>
      </child>
      <child t='167' id='125' V167='21' V283='2' occurMaxTimes='1' minSize='-1' maxSize='-1' dataType='2' elemType='5' repHandlerStruct='' visible='true' inheritsFrom='' V281='13' V1='4' name='I' description='Cost Correction'>
        <structNode t='150' idref='1'/>
      </child>
    </child>
    <child t='167' id='126' V167='21' V283='2' occurMaxTimes='1' minSize='1' maxSize='1' dataType='2' repHandlerStruct='' visible='true' inheritsFrom='' V281='13' V1='4' name='GROUPCOND' description='Group Condition'>
      <structNode t='150' idref='1'/>
      <child t='167' id='127' V167='21' V283='2' occurMaxTimes='1' minSize='-1' maxSize='-1' dataType='2' elemType='5' repHandlerStruct='' visible='true' inheritsFrom='' V281='13' V1='4' name='X' description='Group condition'>
        <structNode t='150' idref='1'/>
      </child>
    </child>
    <child t='167' id='128' V167='21' V283='2' occurMaxTimes='1' minSize='1' maxSize='1' dataType='2' repHandlerStruct='' visible='true' inheritsFrom='' V281='13' V1='4' name='COND_UPDAT' description='Condition Update'>
      <structNode t='150' idref='1'/>
      <child t='167' id='129' V167='21' V283='2' occurMaxTimes='1' minSize='-1' maxSize='-1' dataType='2' elemType='5' repHandlerStruct='' visible='true' inheritsFrom='' V281='13' V1='4' name='X' description='Yes'>
        <structNode t='150' idref='1'/>
      </child>
    </child>
    <child t='167' id='130' V167='21' V283='2' occurMaxTimes='1' minSize='2' maxSize='2' dataType='11' dataFormat='213' repHandlerStruct='' visible='true' inheritsFrom='' V281='13' V1='4' name='ACCESS_SEQ' description='Access sequence - Access number (short length)'>
      <structNode t='150' idref='1'/>
    </child>
    <child t='167' id='131' V167='21' V283='2' occurMaxTimes='1' minSize='2' maxSize='2' dataType='11' dataFormat='213' repHandlerStruct='' visible='true' inheritsFrom='' V281='13' V1='4' name='CONDCOUNT' description='Sequential number of the condition'>
      <structNode t='150' idref='1'/>
    </child>
    <child t='167' id='132' V167='21' V283='2' occurMaxTimes='1' minSize='1' maxSize='1' dataType='2' repHandlerStruct='' visible='true' inheritsFrom='' V281='13' V1='4' name='CONDCNTRL' description='Condition Control' checksumValid='true' checksum='sEBdng2prxEpaYY8dZpMyTPkaoY='>
      <structNode t='150' idref='1'/>
      <child t='167' id='133' V167='21' V283='2' occurMaxTimes='1' minSize='-1' maxSize='-1' dataType='2' elemType='5' repHandlerStruct='' visible='true' inheritsFrom='' V281='13' V1='4' name='A' description='Adjust for quantity variance'>
        <structNode t='150' idref='1'/>
      </child>
      <child t='167' id='134' V167='21' V283='2' occurMaxTimes='1' minSize='-1' maxSize='-1' dataType='2' elemType='5' repHandlerStruct='' visible='true' inheritsFrom='' V281='13' V1='4' name='B' description='Free'>
        <structNode t='150' idref='1'/>
      </child>
      <child t='167' id='135' V167='21' V283='2' occurMaxTimes='1' minSize='-1' maxSize='-1' dataType='2' elemType='5' repHandlerStruct='' visible='true' inheritsFrom='' V281='13' V1='4' name='C' description='Changed manually'>
        <structNode t='150' idref='1'/>
      </child>
      <child t='167' id='136' V167='21' V283='2' occurMaxTimes='1' minSize='-1' maxSize='-1' dataType='2' elemType='5' repHandlerStruct='' visible='true' inheritsFrom='' V281='13' V1='4' name='D' description='Fixed'>
        <structNode t='150' idref='1'/>
      </child>
      <child t='167' id='137' V167='21' V283='2' occurMaxTimes='1' minSize='-1' maxSize='-1' dataType='2' elemType='5' repHandlerStruct='' visible='true' inheritsFrom='' V281='13' V1='4' name='E' description='Condition value and basis fixed'>
        <structNode t='150' idref='1'/>
      </child>
      <child t='167' id='138' V167='21' V283='2' occurMaxTimes='1' minSize='-1' maxSize='-1' dataType='2' elemType='5' repHandlerStruct='' visible='true' inheritsFrom='' V281='13' V1='4' name='F' description='Condition value fixed (billed items)'>
        <structNode t='150' idref='1'/>
      </child>
      <child t='167' id='139' V167='21' V283='2' occurMaxTimes='1' minSize='-1' maxSize='-1' dataType='2' elemType='5' repHandlerStruct='' visible='true' inheritsFrom='' V281='13' V1='4' name='G' description='Condition basis fixed'>
        <structNode t='150' idref='1'/>
      </child>
      <child t='167' id='140' V167='21' V283='2' occurMaxTimes='1' minSize='-1' maxSize='-1' dataType='2' elemType='5' repHandlerStruct='' visible='true' inheritsFrom='' V281='13' V1='4' name='H' description='Condition value fixed (cost price)'>
        <structNode t='150' idref='1'/>
      </child>
      <child t='167' id='141' V167='21' V283='2' occurMaxTimes='1' minSize='-1' maxSize='-1' dataType='2' elemType='5' repHandlerStruct='' visible='true' inheritsFrom='' V281='13' V1='4' name='I' description='Scale Base Value and Condition Amount Fixed (for BYD only)'>
        <structNode t='150' idref='1'/>
      </child>
    </child>
    <child t='167' id='142' V167='21' V283='2' occurMaxTimes='1' minSize='1' maxSize='1' dataType='2' repHandlerStruct='' visible='true' inheritsFrom='' V281='13' V1='4' name='CONDISACTI' description='Condition is Inactive' checksumValid='true' checksum='YY7s9tkpqgRmvEpVQ0hQcwocaug='>
      <structNode t='150' idref='1'/>
      <child t='167' id='143' V167='21' V283='2' occurMaxTimes='1' minSize='-1' maxSize='-1' dataType='2' elemType='5' repHandlerStruct='' visible='true' inheritsFrom='' V281='13' V1='4' name='A' description='Condition exclusion item'>
        <structNode t='150' idref='1'/>
      </child>
      <child t='167' id='144' V167='21' V283='2' occurMaxTimes='1' minSize='-1' maxSize='-1' dataType='2' elemType='5' repHandlerStruct='' visible='true' inheritsFrom='' V281='13' V1='4' name='K' description='Inactive due to calculation basis/shipping material type'>
        <structNode t='150' idref='1'/>
      </child>
      <child t='167' id='145' V167='21' V283='2' occurMaxTimes='1' minSize='-1' maxSize='-1' dataType='2' elemType='5' repHandlerStruct='' visible='true' inheritsFrom='' V281='13' V1='4' name='L' description='Condition exclusion header or inactive at header level'>
        <structNode t='150' idref='1'/>
      </child>
      <child t='167' id='146' V167='21' V283='2' occurMaxTimes='1' minSize='-1' maxSize='-1' dataType='2' elemType='5' repHandlerStruct='' visible='true' inheritsFrom='' V281='13' V1='4' name='M' description='Inactive due to manual entry'>
        <structNode t='150' idref='1'/>
      </child>
      <child t='167' id='147' V167='21' V283='2' occurMaxTimes='1' minSize='-1' maxSize='-1' dataType='2' elemType='5' repHandlerStruct='' visible='true' inheritsFrom='' V281='13' V1='4' name='T' description='Inactive at header level'>
        <structNode t='150' idref='1'/>
      </child>
      <child t='167' id='148' V167='21' V283='2' occurMaxTimes='1' minSize='-1' maxSize='-1' dataType='2' elemType='5' repHandlerStruct='' visible='true' inheritsFrom='' V281='13' V1='4' name='W' description='The document item is statistical'>
        <structNode t='150' idref='1'/>
      </child>
      <child t='167' id='149' V167='21' V283='2' occurMaxTimes='1' minSize='-1' maxSize='-1' dataType='2' elemType='5' repHandlerStruct='' visible='true' inheritsFrom='' V281='13' V1='4' name='X' description='Inactive via formulas or incorrect'>
        <structNode t='150' idref='1'/>
      </child>
      <child t='167' id='150' V167='21' V283='2' occurMaxTimes='1' minSize='-1' maxSize='-1' dataType='2' elemType='5' repHandlerStruct='' visible='true' inheritsFrom='' V281='13' V1='4' name='Y' description='Inactive because of subsequent price'>
        <structNode t='150' idref='1'/>
      </child>
    </child>
    <child t='167' id='151' V167='21' V283='2' occurMaxTimes='1' minSize='1' maxSize='1' dataType='2' repHandlerStruct='' visible='true' inheritsFrom='' V281='13' V1='4' name='CONDCLASS' description='Condition Class' checksumValid='true' checksum='YWdkz0Kf1viziwLD2UBrbZbyz4U='>
      <structNode t='150' idref='1'/>
      <child t='167' id='152' V167='21' V283='2' occurMaxTimes='1' minSize='-1' maxSize='-1' dataType='2' elemType='5' repHandlerStruct='' visible='true' inheritsFrom='' V281='13' V1='4' name='A' description='Discount or surcharge'>
        <structNode t='150' idref='1'/>
      </child>
      <child t='167' id='153' V167='21' V283='2' occurMaxTimes='1' minSize='-1' maxSize='-1' dataType='2' elemType='5' repHandlerStruct='' visible='true' inheritsFrom='' V281='13' V1='4' name='B' description='Prices'>
        <structNode t='150' idref='1'/>
      </child>
      <child t='167' id='154' V167='21' V283='2' occurMaxTimes='1' minSize='-1' maxSize='-1' dataType='2' elemType='5' repHandlerStruct='' visible='true' inheritsFrom='' V281='13' V1='4' name='C' description='Expense reimbursement'>
        <structNode t='150' idref='1'/>
      </child>
      <child t='167' id='155' V167='21' V283='2' occurMaxTimes='1' minSize='-1' maxSize='-1' dataType='2' elemType='5' repHandlerStruct='' visible='true' inheritsFrom='' V281='13' V1='4' name='D' description='Taxes'>
        <structNode t='150' idref='1'/>
      </child>
      <child t='167' id='156' V167='21' V283='2' occurMaxTimes='1' minSize='-1' maxSize='-1' dataType='2' elemType='5' repHandlerStruct='' visible='true' inheritsFrom='' V281='13' V1='4' name='E' description='Extra pay'>
        <structNode t='150' idref='1'/>
      </child>
      <child t='167' id='157' V167='21' V283='2' occurMaxTimes='1' minSize='-1' maxSize='-1' dataType='2' elemType='5' repHandlerStruct='' visible='true' inheritsFrom='' V281='13' V1='4' name='F' description='Fees or differential (only IS-OIL)'>
        <structNode t='150' idref='1'/>
      </child>
      <child t='167' id='158' V167='21' V283='2' occurMaxTimes='1' minSize='-1' maxSize='-1' dataType='2' elemType='5' repHandlerStruct='' visible='true' inheritsFrom='' V281='13' V1='4' name='G' description='Tax Classification'>
        <structNode t='150' idref='1'/>
      </child>
      <child t='167' id='159' V167='21' V283='2' occurMaxTimes='1' minSize='-1' maxSize='-1' dataType='2' elemType='5' repHandlerStruct='' visible='true' inheritsFrom='' V281='13' V1='4' name='H' description='Determining sales deal'>
        <structNode t='150' idref='1'/>
      </child>
      <child t='167' id='160' V167='21' V283='2' occurMaxTimes='1' minSize='-1' maxSize='-1' dataType='2' elemType='5' repHandlerStruct='' visible='true' inheritsFrom='' V281='13' V1='4' name='Q' description='Totals record for fees (only IS-OIL)'>
        <structNode t='150' idref='1'/>
      </child>
      <child t='167' id='161' V167='21' V283='2' occurMaxTimes='1' minSize='-1' maxSize='-1' dataType='2' elemType='5' repHandlerStruct='' visible='true' inheritsFrom='' V281='13' V1='4' name='W' description='Wage Withholding Tax'>
        <structNode t='150' idref='1'/>
      </child>
      <child t='167' id='162' V167='21' V283='2' occurMaxTimes='1' minSize='-1' maxSize='-1' dataType='2' elemType='5' repHandlerStruct='' visible='true' inheritsFrom='' V281='13' V1='4' name='P' description='Compare Price Protection'>
        <structNode t='150' idref='1'/>
      </child>
    </child>
    <child t='167' id='163' V167='21' V283='2' occurMaxTimes='1' minSize='24' maxSize='24' dataType='21' repHandlerStruct='' visible='true' inheritsFrom='' V281='13' V1='4' name='FACTBASVAL' description='Factor for Condition Base Value'>
      <structNode t='150' idref='1'/>
    </child>
    <child t='167' id='164' V167='21' V283='2' occurMaxTimes='1' minSize='1' maxSize='1' dataType='2' repHandlerStruct='' visible='true' inheritsFrom='' V281='13' V1='4' name='SCALEBASIN' description='Scale Basis Indicator' checksumValid='true' checksum='ls7K4GYz0RkU53NWY5FzCfUFx30='>
      <structNode t='150' idref='1'/>
      <child t='167' id='165' V167='21' V283='2' occurMaxTimes='1' minSize='-1' maxSize='-1' dataType='2' elemType='5' repHandlerStruct='' visible='true' inheritsFrom='' V281='13' V1='4' name='B' description='Value scale'>
        <structNode t='150' idref='1'/>
      </child>
      <child t='167' id='166' V167='21' V283='2' occurMaxTimes='1' minSize='-1' maxSize='-1' dataType='2' elemType='5' repHandlerStruct='' visible='true' inheritsFrom='' V281='13' V1='4' name='C' description='Quantity scale'>
        <structNode t='150' idref='1'/>
      </child>
      <child t='167' id='167' V167='21' V283='2' occurMaxTimes='1' minSize='-1' maxSize='-1' dataType='2' elemType='5' repHandlerStruct='' visible='true' inheritsFrom='' V281='13' V1='4' name='D' description='Gross weight scale'>
        <structNode t='150' idref='1'/>
      </child>
      <child t='167' id='168' V167='21' V283='2' occurMaxTimes='1' minSize='-1' maxSize='-1' dataType='2' elemType='5' repHandlerStruct='' visible='true' inheritsFrom='' V281='13' V1='4' name='E' description='Net weight scale'>
        <structNode t='150' idref='1'/>
      </child>
      <child t='167' id='169' V167='21' V283='2' occurMaxTimes='1' minSize='-1' maxSize='-1' dataType='2' elemType='5' repHandlerStruct='' visible='true' inheritsFrom='' V281='13' V1='4' name='F' description='Volume scale'>
        <structNode t='150' idref='1'/>
      </child>
      <child t='167' id='170' V167='21' V283='2' occurMaxTimes='1' minSize='-1' maxSize='-1' dataType='2' elemType='5' repHandlerStruct='' visible='true' inheritsFrom='' V281='13' V1='4' name='G' description='Scale based on a formula'>
        <structNode t='150' idref='1'/>
      </child>
      <child t='167' id='171' V167='21' V283='2' occurMaxTimes='1' minSize='-1' maxSize='-1' dataType='2' elemType='5' repHandlerStruct='' visible='true' inheritsFrom='' V281='13' V1='4' name='L' description='Point scale'>
        <structNode t='150' idref='1'/>
      </child>
      <child t='167' id='172' V167='21' V283='2' occurMaxTimes='1' minSize='-1' maxSize='-1' dataType='2' elemType='5' repHandlerStruct='' visible='true' inheritsFrom='' V281='13' V1='4' name='M' description='Time period scale - Month'>
        <structNode t='150' idref='1'/>
      </child>
      <child t='167' id='173' V167='21' V283='2' occurMaxTimes='1' minSize='-1' maxSize='-1' dataType='2' elemType='5' repHandlerStruct='' visible='true' inheritsFrom='' V281='13' V1='4' name='N' description='Time period scale - Years'>
        <structNode t='150' idref='1'/>
      </child>
      <child t='167' id='174' V167='21' V283='2' occurMaxTimes='1' minSize='-1' maxSize='-1' dataType='2' elemType='5' repHandlerStruct='' visible='true' inheritsFrom='' V281='13' V1='4' name='O' description='Time period scale - Days'>
        <structNode t='150' idref='1'/>
      </child>
      <child t='167' id='175' V167='21' V283='2' occurMaxTimes='1' minSize='-1' maxSize='-1' dataType='2' elemType='5' repHandlerStruct='' visible='true' inheritsFrom='' V281='13' V1='4' name='P' description='Time period scale - Week'>
        <structNode t='150' idref='1'/>
      </child>
      <child t='167' id='176' V167='21' V283='2' occurMaxTimes='1' minSize='-1' maxSize='-1' dataType='2' elemType='5' repHandlerStruct='' visible='true' inheritsFrom='' V281='13' V1='4' name='R' description='Distance'>
        <structNode t='150' idref='1'/>
      </child>
      <child t='167' id='177' V167='21' V283='2' occurMaxTimes='1' minSize='-1' maxSize='-1' dataType='2' elemType='5' repHandlerStruct='' visible='true' inheritsFrom='' V281='13' V1='4' name='S' description='Number of shipping units'>
        <structNode t='150' idref='1'/>
      </child>
      <child t='167' id='178' V167='21' V283='2' occurMaxTimes='1' minSize='-1' maxSize='-1' dataType='2' elemType='5' repHandlerStruct='' visible='true' inheritsFrom='' V281='13' V1='4' name='T' description='Reserved (IS-OIL, time prices)'>
        <structNode t='150' idref='1'/>
      </child>
      <child t='167' id='179' V167='21' V283='2' occurMaxTimes='1' minSize='-1' maxSize='-1' dataType='2' elemType='5' repHandlerStruct='' visible='true' inheritsFrom='' V281='13' V1='4' name='X' description='Reserved (IS-OIL, day prices)'>
        <structNode t='150' idref='1'/>
      </child>
    </child>
    <child t='167' id='180' V167='21' V283='2' occurMaxTimes='1' minSize='31' maxSize='31' dataType='22' dataFormat='212' repHandlerStruct='' visible='true' inheritsFrom='' V281='13' V1='4' name='SCALBASVAL' description='Scale base value of the condition'>
      <structNode t='150' idref='1'/>
    </child>
    <child t='167' id='181' V167='21' V283='2' occurMaxTimes='1' minSize='3' maxSize='3' dataType='2' repHandlerStruct='' visible='true' inheritsFrom='' V281='13' V1='4' name='UNITMEASUR' description='Condition Scale Unit of Measure'>
      <structNode t='150' idref='1'/>
    </child>
    <child t='167' id='182' V167='21' V283='2' occurMaxTimes='1' minSize='3' maxSize='3' dataType='2' repHandlerStruct='' visible='true' inheritsFrom='' V281='13' V1='4' name='UNITMEASUR_ISO' description='ISO code for unit of measurement'>
      <structNode t='150' idref='1'/>
    </child>
    <child t='167' id='183' V167='21' V283='2' occurMaxTimes='1' minSize='5' maxSize='5' dataType='2' repHandlerStruct='' visible='true' inheritsFrom='' V281='13' V1='4' name='CURRENCKEY' description='Scale Currency'>
      <structNode t='150' idref='1'/>
    </child>
    <child t='167' id='184' V167='21' V283='2' occurMaxTimes='1' minSize='3' maxSize='3' dataType='2' repHandlerStruct='' visible='true' inheritsFrom='' V281='13' V1='4' name='CURRENCKEY_ISO' description='ISO code currency'>
      <structNode t='150' idref='1'/>
    </child>
    <child t='167' id='185' V167='21' V283='2' occurMaxTimes='1' minSize='1' maxSize='1' dataType='2' repHandlerStruct='' visible='true' inheritsFrom='' V281='13' V1='4' name='CONDINCOMP' description='Condition for Intercompany Billing'>
      <structNode t='150' idref='1'/>
      <child t='167' id='186' V167='21' V283='2' occurMaxTimes='1' minSize='-1' maxSize='-1' dataType='2' elemType='5' repHandlerStruct='' visible='true' inheritsFrom='' V281='13' V1='4' name='X' description='Yes'>
        <structNode t='150' idref='1'/>
      </child>
    </child>
    <child t='167' id='187' V167='21' V283='2' occurMaxTimes='1' minSize='1' maxSize='1' dataType='2' repHandlerStruct='' visible='true' inheritsFrom='' V281='13' V1='4' name='CONDCONFIG' description='Condition for Configuration'>
      <structNode t='150' idref='1'/>
      <child t='167' id='188' V167='21' V283='2' occurMaxTimes='1' minSize='-1' maxSize='-1' dataType='2' elemType='5' repHandlerStruct='' visible='true' inheritsFrom='' V281='13' V1='4' name='X' description='Yes'>
        <structNode t='150' idref='1'/>
      </child>
    </child>
    <child t='167' id='189' V167='21' V283='2' occurMaxTimes='1' minSize='1' maxSize='1' dataType='2' repHandlerStruct='' visible='true' inheritsFrom='' V281='13' V1='4' name='CONDCHAMAN' description='Condition Changed Manually'>
      <structNode t='150' idref='1'/>
      <child t='167' id='190' V167='21' V283='2' occurMaxTimes='1' minSize='-1' maxSize='-1' dataType='2' elemType='5' repHandlerStruct='' visible='true' inheritsFrom='' V281='13' V1='4' name='X' description='Yes'>
        <structNode t='150' idref='1'/>
      </child>
    </child>
    <child t='167' id='191' V167='21' V283='2' occurMaxTimes='1' minSize='10' maxSize='10' dataType='2' repHandlerStruct='' visible='true' inheritsFrom='' V281='13' V1='4' name='COND_NO' description='Condition record number'>
      <structNode t='150' idref='1'/>
    </child>
    <child t='167' id='192' V167='21' V283='2' occurMaxTimes='1' minSize='1' maxSize='1' dataType='2' repHandlerStruct='' visible='true' inheritsFrom='' V281='13' V1='4' name='CHANGE_ID' description='Type of Change'>
      <structNode t='150' idref='1'/>
      <child t='167' id='193' V167='21' V283='2' occurMaxTimes='1' minSize='-1' maxSize='-1' dataType='2' elemType='5' repHandlerStruct='' visible='true' inheritsFrom='' V281='13' V1='4' name='U' description='Change'>
        <structNode t='150' idref='1'/>
      </child>
      <child t='167' id='194' V167='21' V283='2' occurMaxTimes='1' minSize='-1' maxSize='-1' dataType='2' elemType='5' repHandlerStruct='' visible='true' inheritsFrom='' V281='13' V1='4' name='I' description='Insert'>
        <structNode t='150' idref='1'/>
      </child>
      <child t='167' id='195' V167='21' V283='2' occurMaxTimes='1' minSize='-1' maxSize='-1' dataType='2' elemType='5' repHandlerStruct='' visible='true' inheritsFrom='' V281='13' V1='4' name='E' description='Delete (single field documentation)'>
        <structNode t='150' idref='1'/>
      </child>
      <child t='167' id='196' V167='21' V283='2' occurMaxTimes='1' minSize='-1' maxSize='-1' dataType='2' elemType='5' repHandlerStruct='' visible='true' inheritsFrom='' V281='13' V1='4' name='D' description='Delete'>
        <structNode t='150' idref='1'/>
      </child>
      <child t='167' id='197' V167='21' V283='2' occurMaxTimes='1' minSize='-1' maxSize='-1' dataType='2' elemType='5' repHandlerStruct='' visible='true' inheritsFrom='' V281='13' V1='4' name='J' description='Insert (single field documentation)'>
        <structNode t='150' idref='1'/>
      </child>
    </child>
    <child t='167' id='198' V167='21' V283='2' occurMaxTimes='1' minSize='10' maxSize='10' dataType='2' repHandlerStruct='' visible='true' inheritsFrom='' V281='13' V1='4' name='VENDOR_NO' description='Account Number of Vendor or Creditor'>
      <structNode t='150' idref='1'/>
    </child>
    <child t='167' id='199' V167='21' V283='2' occurMaxTimes='1' minSize='3' maxSize='3' dataType='12' dataFormat='213' repHandlerStruct='' visible='true' inheritsFrom='' V281='13' V1='4' name='ACCESS_SEQ_LONG' description='Access sequence - Access number'>
      <structNode t='150' idref='1'/>
    </child>
    <child t='167' id='200' V167='21' V283='2' occurMaxTimes='1' minSize='3' maxSize='3' dataType='12' dataFormat='213' repHandlerStruct='' visible='true' inheritsFrom='' V281='13' V1='4' name='COND_COUNT_LONG' description='Condition Counter'>
      <structNode t='150' idref='1'/>
    </child>
  </rootElem>
  <defaultRep t='181' id='201' V181='1' V170='10' V704='1' V690='1' encoding='UTF-8' ignoreExcluded='true' fixInvalidCharacters='true' V1='4' name='IDocs'>
  </defaultRep>
  <child t='162' id='202' V1='4' name='Representations'>
    <child t='181' idref='201'/>
    <child t='172' id='203' V172='6' autoFixNamespaceMismatch='true' V170='10' V692='1' V690='1' ignoreExcluded='true' fixInvalidCharacters='true' V1='4' name='XML'>
    </child>
  </child>
  <child t='165' id='204' V1='4' name='Document Bindings'>
  </child>
</root>
