<?xml version="1.0" encoding="UTF-8"?>
<root t='150' id='1' V150='13' creationTimestamp='0x16d16668bb3' V1='4' name='SALESORDER_CREATEFROMDAT204' incarnation='104'>
  <rootElem t='167' id='2' V167='21' V283='2' occurMaxTimes='1' minSize='-1' maxSize='-1' groupType='1' repHandlerStruct='' visible='true' inheritsFrom='' V281='13' V1='4' name='SALESORDER_CREATEFROMDAT204' description='Sales order: Create Sales Order'>
    <structNode t='150' idref='1'/>
    <child t='167' id='3' V167='21' inheritsFromIncarnation='40' inheritsFromTimestamp='0x16d16668b94' inheritsInThisStruct='true' V283='2' occurMinTimes='1' occurMaxTimes='1' minSize='-1' maxSize='-1' inheritsFromCopyRule='28' groupType='1' repHandlerStruct='' visible='true' inheritsFrom='Structures/Segments/EDI_DC40.xml' V281='13' V1='4' name='EDI_DC40' description='Control record' checksumValid='true' checksum='vax6NvhvPeJnlh2EY9OkLDGqRTE='>
      <structNode t='150' idref='1'/>
      <savedDerivedCopy t='167' id='4' V167='21' needInheritInit='true' inheritsInThisStruct='true' V283='2' occurMaxTimes='1' minSize='-1' maxSize='-1' dataType='2' repHandlerStruct='' visible='true' inheritsFrom='Structures/Segments/EDI_DC40.xml' V281='13' V1='4' name='EDI_DC40'>
      </savedDerivedCopy>
      <savedOrigCopyAtInheritsFrom t='167' id='5' V167='21' V283='2' occurMaxTimes='1' minSize='-1' maxSize='-1' groupType='1' repHandlerStruct='' visible='true' inheritsFrom='' V281='13' V1='4' name='EDI_DC40' description='Control record'>
        <delimTerminator>\n</delimTerminator>
      </savedOrigCopyAtInheritsFrom>
      <delimTerminator>\n</delimTerminator>
    </child>
    <child t='167' id='6' V167='21' V283='2' occurMaxTimes='1' minSize='-1' maxSize='-1' groupType='1' repHandlerStruct='' visible='true' inheritsFrom='' V281='13' V1='4' name='Loop-E2SALESORDER_CREATEFROMDAT2000' description='Header Segment' checksumValid='true' checksum='ak6KTu5tY6Lds1sWdKCxOPdfm2U='>
      <structNode t='150' idref='1'/>
      <child t='167' id='7' V167='21' inheritsFromIncarnation='20' inheritsFromTimestamp='0x16d16668ba3' inheritsInThisStruct='true' V283='2' occurMinTimes='1' occurMaxTimes='1' minSize='-1' maxSize='-1' inheritsFromCopyRule='28' groupType='1' repHandlerStruct='' visible='true' inheritsFrom='Structures/Segments/E2SALESORDER_CREATEFROMDAT2000.xml' V281='13' V1='4' name='E2SALESORDER_CREATEFROMDAT2000' description='Header Segment' checksumValid='true' checksum='/D+0KiDZvLOyRsQU0SXRaFA7ciQ='>
        <structNode t='150' idref='1'/>
        <savedDerivedCopy t='167' id='8' V167='21' needInheritInit='true' inheritsInThisStruct='true' V283='2' occurMaxTimes='1' minSize='-1' maxSize='-1' dataType='2' repHandlerStruct='' visible='true' inheritsFrom='Structures/Segments/E2SALESORDER_CREATEFROMDAT2000.xml' V281='13' V1='4' name='E2SALESORDER_CREATEFROMDAT2000'>
        </savedDerivedCopy>
        <savedOrigCopyAtInheritsFrom t='167' id='9' V167='21' V283='2' occurMaxTimes='1' minSize='-1' maxSize='-1' groupType='1' repHandlerStruct='' visible='true' inheritsFrom='' V281='13' V1='4' name='E2SALESORDER_CREATEFROMDAT2000' description='Header Segment'>
          <delimTerminator>\n</delimTerminator>
        </savedOrigCopyAtInheritsFrom>
        <delimTerminator>\n</delimTerminator>
      </child>
      <child t='167' id='10' V167='21' V283='2' occurMaxTimes='1' minSize='-1' maxSize='-1' groupType='1' repHandlerStruct='' visible='true' inheritsFrom='' V281='13' V1='4' name='Loop-E2BPSDHD1002' description='Communication Fields: Sales and Distribution Document Header'>
        <structNode t='150' idref='1'/>
        <child t='167' id='11' V167='21' inheritsFromIncarnation='283' inheritsFromTimestamp='0x16d16668ba3' inheritsInThisStruct='true' V283='2' occurMinTimes='1' occurMaxTimes='1' minSize='-1' maxSize='-1' inheritsFromCopyRule='28' groupType='1' repHandlerStruct='' visible='true' inheritsFrom='Structures/Segments/E2BPSDHD1002.xml' V281='13' V1='4' name='E2BPSDHD1002' description='Communication Fields: Sales and Distribution Document Header' checksumValid='true' checksum='ZXWxTKSqKC6U9KZD0lUolMdNkhk='>
          <structNode t='150' idref='1'/>
          <savedDerivedCopy t='167' id='12' V167='21' needInheritInit='true' inheritsInThisStruct='true' V283='2' occurMaxTimes='1' minSize='-1' maxSize='-1' dataType='2' repHandlerStruct='' visible='true' inheritsFrom='Structures/Segments/E2BPSDHD1002.xml' V281='13' V1='4' name='E2BPSDHD1002'>
          </savedDerivedCopy>
          <savedOrigCopyAtInheritsFrom t='167' id='13' V167='21' V283='2' occurMaxTimes='1' minSize='-1' maxSize='-1' groupType='1' repHandlerStruct='' visible='true' inheritsFrom='' V281='13' V1='4' name='E2BPSDHD1002' description='Communication Fields: Sales and Distribution Document Header'>
            <delimTerminator>\n</delimTerminator>
          </savedOrigCopyAtInheritsFrom>
          <delimTerminator>\n</delimTerminator>
        </child>
        <child t='167' id='14' V167='21' inheritsFromIncarnation='98' inheritsFromTimestamp='0x16d16668ba3' inheritsInThisStruct='true' V283='2' occurMaxTimes='1' minSize='-1' maxSize='-1' inheritsFromCopyRule='28' groupType='1' repHandlerStruct='' visible='true' inheritsFrom='Structures/Segments/E2BPSDHD11001.xml' V281='13' V1='4' name='E2BPSDHD11001' description='Communication Fields: Sales and Distribution Document Header' checksumValid='true' checksum='5ssLVmBERKsqYByJXMdFlDMusBA='>
          <structNode t='150' idref='1'/>
          <savedDerivedCopy t='167' id='15' V167='21' needInheritInit='true' inheritsInThisStruct='true' V283='2' occurMaxTimes='1' minSize='-1' maxSize='-1' dataType='2' repHandlerStruct='' visible='true' inheritsFrom='Structures/Segments/E2BPSDHD11001.xml' V281='13' V1='4' name='E2BPSDHD11001'>
          </savedDerivedCopy>
          <savedOrigCopyAtInheritsFrom t='167' id='16' V167='21' V283='2' occurMaxTimes='1' minSize='-1' maxSize='-1' groupType='1' repHandlerStruct='' visible='true' inheritsFrom='' V281='13' V1='4' name='E2BPSDHD11001' description='Communication Fields: Sales and Distribution Document Header'>
            <delimTerminator>\n</delimTerminator>
          </savedOrigCopyAtInheritsFrom>
          <delimTerminator>\n</delimTerminator>
        </child>
      </child>
      <child t='167' id='17' V167='21' inheritsFromIncarnation='265' inheritsFromTimestamp='0x16d16668ba3' inheritsInThisStruct='true' V283='2' occurMaxTimes='1' minSize='-1' maxSize='-1' inheritsFromCopyRule='28' groupType='1' repHandlerStruct='' visible='true' inheritsFrom='Structures/Segments/E2BPSDHD1X003.xml' V281='13' V1='4' name='E2BPSDHD1X003' description='Checkbox Fields for Sales and Distribution Document Header' checksumValid='true' checksum='E7HSB2BHvuIKz+uZx03Gg01sqT8='>
        <structNode t='150' idref='1'/>
        <savedDerivedCopy t='167' id='18' V167='21' needInheritInit='true' inheritsInThisStruct='true' V283='2' occurMaxTimes='1' minSize='-1' maxSize='-1' dataType='2' repHandlerStruct='' visible='true' inheritsFrom='Structures/Segments/E2BPSDHD1X003.xml' V281='13' V1='4' name='E2BPSDHD1X003'>
        </savedDerivedCopy>
        <savedOrigCopyAtInheritsFrom t='167' id='19' V167='21' V283='2' occurMaxTimes='1' minSize='-1' maxSize='-1' groupType='1' repHandlerStruct='' visible='true' inheritsFrom='' V281='13' V1='4' name='E2BPSDHD1X003' description='Checkbox Fields for Sales and Distribution Document Header'>
          <delimTerminator>\n</delimTerminator>
        </savedOrigCopyAtInheritsFrom>
        <delimTerminator>\n</delimTerminator>
      </child>
      <child t='167' id='20' V167='21' inheritsFromIncarnation='15' inheritsFromTimestamp='0x16d16668ba3' inheritsInThisStruct='true' V283='2' occurMaxTimes='1' minSize='-1' maxSize='-1' inheritsFromCopyRule='28' groupType='1' repHandlerStruct='' visible='true' inheritsFrom='Structures/Segments/E2BP_SENDER000.xml' V281='13' V1='4' name='E2BP_SENDER000' description='Logical System of Sender'>
        <structNode t='150' idref='1'/>
        <savedDerivedCopy t='167' id='21' V167='21' needInheritInit='true' inheritsInThisStruct='true' V283='2' occurMaxTimes='1' minSize='-1' maxSize='-1' dataType='2' repHandlerStruct='' visible='true' inheritsFrom='Structures/Segments/E2BP_SENDER000.xml' V281='13' V1='4' name='E2BP_SENDER000'>
        </savedDerivedCopy>
        <savedOrigCopyAtInheritsFrom t='167' id='22' V167='21' V283='2' occurMaxTimes='1' minSize='-1' maxSize='-1' groupType='1' repHandlerStruct='' visible='true' inheritsFrom='' V281='13' V1='4' name='E2BP_SENDER000' description='Logical System of Sender'>
          <delimTerminator>\n</delimTerminator>
        </savedOrigCopyAtInheritsFrom>
        <delimTerminator>\n</delimTerminator>
      </child>
      <child t='167' id='23' V167='21' inheritsFromIncarnation='52' inheritsFromTimestamp='0x16d16668ba3' inheritsInThisStruct='true' V283='2' occurMaxTimes='1' minSize='-1' maxSize='-1' inheritsFromCopyRule='28' groupType='1' repHandlerStruct='' visible='true' inheritsFrom='Structures/Segments/E2BPSDLS001.xml' V281='13' V1='4' name='E2BPSDLS001' description='SD Checkbox for the Logic Switch' checksumValid='true' checksum='QgdeuxnEx5Kevx+8RzaSQ2YeaB4='>
        <structNode t='150' idref='1'/>
        <savedDerivedCopy t='167' id='24' V167='21' needInheritInit='true' inheritsInThisStruct='true' V283='2' occurMaxTimes='1' minSize='-1' maxSize='-1' dataType='2' repHandlerStruct='' visible='true' inheritsFrom='Structures/Segments/E2BPSDLS001.xml' V281='13' V1='4' name='E2BPSDLS001'>
        </savedDerivedCopy>
        <savedOrigCopyAtInheritsFrom t='167' id='25' V167='21' V283='2' occurMaxTimes='1' minSize='-1' maxSize='-1' groupType='1' repHandlerStruct='' visible='true' inheritsFrom='' V281='13' V1='4' name='E2BPSDLS001' description='SD Checkbox for the Logic Switch'>
          <delimTerminator>\n</delimTerminator>
        </savedOrigCopyAtInheritsFrom>
        <delimTerminator>\n</delimTerminator>
      </child>
      <child t='167' id='26' V167='21' V283='2' occurMaxTimes='999999999' minSize='-1' maxSize='-1' groupType='1' repHandlerStruct='' visible='true' inheritsFrom='' V281='13' V1='4' name='Loop-E2BPSDITM000' description='Communication Fields: Sales and Distribution Document Item'>
        <structNode t='150' idref='1'/>
        <child t='167' id='27' V167='21' inheritsFromIncarnation='170' inheritsFromTimestamp='0x16d16668ba3' inheritsInThisStruct='true' V283='2' occurMinTimes='1' occurMaxTimes='1' minSize='-1' maxSize='-1' inheritsFromCopyRule='28' groupType='1' repHandlerStruct='' visible='true' inheritsFrom='Structures/Segments/E2BPSDITM000.xml' V281='13' V1='4' name='E2BPSDITM000' description='Communication Fields: Sales and Distribution Document Item' checksumValid='true' checksum='YePeCQlAZsRIEJEVCZduIpaUGmk='>
          <structNode t='150' idref='1'/>
          <savedDerivedCopy t='167' id='28' V167='21' needInheritInit='true' inheritsInThisStruct='true' V283='2' occurMaxTimes='1' minSize='-1' maxSize='-1' dataType='2' repHandlerStruct='' visible='true' inheritsFrom='Structures/Segments/E2BPSDITM000.xml' V281='13' V1='4' name='E2BPSDITM000'>
          </savedDerivedCopy>
          <savedOrigCopyAtInheritsFrom t='167' id='29' V167='21' V283='2' occurMaxTimes='1' minSize='-1' maxSize='-1' groupType='1' repHandlerStruct='' visible='true' inheritsFrom='' V281='13' V1='4' name='E2BPSDITM000' description='Communication Fields: Sales and Distribution Document Item'>
            <delimTerminator>\n</delimTerminator>
          </savedOrigCopyAtInheritsFrom>
          <delimTerminator>\n</delimTerminator>
        </child>
        <child t='167' id='30' V167='21' V283='2' occurMaxTimes='1' minSize='-1' maxSize='-1' groupType='1' repHandlerStruct='' visible='true' inheritsFrom='' V281='13' V1='4' name='Loop-E2BPSDITM1004' description='Communication Fields: Sales and Distribution Document Item'>
          <structNode t='150' idref='1'/>
          <child t='167' id='31' V167='21' inheritsFromIncarnation='261' inheritsFromTimestamp='0x16d16668ba3' inheritsInThisStruct='true' V283='2' occurMinTimes='1' occurMaxTimes='1' minSize='-1' maxSize='-1' inheritsFromCopyRule='28' groupType='1' repHandlerStruct='' visible='true' inheritsFrom='Structures/Segments/E2BPSDITM1004.xml' V281='13' V1='4' name='E2BPSDITM1004' description='Communication Fields: Sales and Distribution Document Item' checksumValid='true' checksum='8wgn4V7/YKaJbKXELEKg8hKTvv0='>
            <structNode t='150' idref='1'/>
            <savedDerivedCopy t='167' id='32' V167='21' needInheritInit='true' inheritsInThisStruct='true' V283='2' occurMaxTimes='1' minSize='-1' maxSize='-1' dataType='2' repHandlerStruct='' visible='true' inheritsFrom='Structures/Segments/E2BPSDITM1004.xml' V281='13' V1='4' name='E2BPSDITM1004'>
            </savedDerivedCopy>
            <savedOrigCopyAtInheritsFrom t='167' id='33' V167='21' V283='2' occurMaxTimes='1' minSize='-1' maxSize='-1' groupType='1' repHandlerStruct='' visible='true' inheritsFrom='' V281='13' V1='4' name='E2BPSDITM1004' description='Communication Fields: Sales and Distribution Document Item'>
              <delimTerminator>\n</delimTerminator>
            </savedOrigCopyAtInheritsFrom>
            <delimTerminator>\n</delimTerminator>
          </child>
          <child t='167' id='34' V167='21' inheritsFromIncarnation='21' inheritsFromTimestamp='0x16d16668bb3' inheritsInThisStruct='true' V283='2' occurMaxTimes='1' minSize='-1' maxSize='-1' inheritsFromCopyRule='28' groupType='1' repHandlerStruct='' visible='true' inheritsFrom='Structures/Segments/E2BPSDITM2001.xml' V281='13' V1='4' name='E2BPSDITM2001' description='Communication Fields: Sales and Distribution Document Item' checksumValid='true' checksum='t4qAnyxFPez02LEy9VziSWdOJ8M='>
            <structNode t='150' idref='1'/>
            <savedDerivedCopy t='167' id='35' V167='21' needInheritInit='true' inheritsInThisStruct='true' V283='2' occurMaxTimes='1' minSize='-1' maxSize='-1' dataType='2' repHandlerStruct='' visible='true' inheritsFrom='Structures/Segments/E2BPSDITM2001.xml' V281='13' V1='4' name='E2BPSDITM2001'>
            </savedDerivedCopy>
            <savedOrigCopyAtInheritsFrom t='167' id='36' V167='21' V283='2' occurMaxTimes='1' minSize='-1' maxSize='-1' groupType='1' repHandlerStruct='' visible='true' inheritsFrom='' V281='13' V1='4' name='E2BPSDITM2001' description='Communication Fields: Sales and Distribution Document Item'>
              <delimTerminator>\n</delimTerminator>
            </savedOrigCopyAtInheritsFrom>
            <delimTerminator>\n</delimTerminator>
          </child>
        </child>
      </child>
      <child t='167' id='37' V167='21' inheritsFromIncarnation='440' inheritsFromTimestamp='0x16d16668bb3' inheritsInThisStruct='true' V283='2' occurMaxTimes='999999999' minSize='-1' maxSize='-1' inheritsFromCopyRule='28' groupType='1' repHandlerStruct='' visible='true' inheritsFrom='Structures/Segments/E2BPSDITMX005.xml' V281='13' V1='4' name='E2BPSDITMX005' description='Communication Fields: Sales and Distribution Document Item' checksumValid='true' checksum='I9rN/v2RxZEwbyx5R+VzqtbUdtQ='>
        <structNode t='150' idref='1'/>
        <savedDerivedCopy t='167' id='38' V167='21' needInheritInit='true' inheritsInThisStruct='true' V283='2' occurMaxTimes='1' minSize='-1' maxSize='-1' dataType='2' repHandlerStruct='' visible='true' inheritsFrom='Structures/Segments/E2BPSDITMX005.xml' V281='13' V1='4' name='E2BPSDITMX005'>
        </savedDerivedCopy>
        <savedOrigCopyAtInheritsFrom t='167' id='39' V167='21' V283='2' occurMaxTimes='1' minSize='-1' maxSize='-1' groupType='1' repHandlerStruct='' visible='true' inheritsFrom='' V281='13' V1='4' name='E2BPSDITMX005' description='Communication Fields: Sales and Distribution Document Item'>
          <delimTerminator>\n</delimTerminator>
        </savedOrigCopyAtInheritsFrom>
        <delimTerminator>\n</delimTerminator>
      </child>
      <child t='167' id='40' V167='21' inheritsFromIncarnation='57' inheritsFromTimestamp='0x16d16668bb3' inheritsInThisStruct='true' V283='2' occurMaxTimes='999999999' minSize='-1' maxSize='-1' inheritsFromCopyRule='28' groupType='1' repHandlerStruct='' visible='true' inheritsFrom='Structures/Segments/E2BPPARNR000.xml' V281='13' V1='4' name='E2BPPARNR000' description='Communications Fields: SD Document Partner: WWW' checksumValid='true' checksum='WlhQWTebbWKHm9cXhR1eiwWSIds='>
        <structNode t='150' idref='1'/>
        <savedDerivedCopy t='167' id='41' V167='21' needInheritInit='true' inheritsInThisStruct='true' V283='2' occurMaxTimes='1' minSize='-1' maxSize='-1' dataType='2' repHandlerStruct='' visible='true' inheritsFrom='Structures/Segments/E2BPPARNR000.xml' V281='13' V1='4' name='E2BPPARNR000'>
        </savedDerivedCopy>
        <savedOrigCopyAtInheritsFrom t='167' id='42' V167='21' V283='2' occurMaxTimes='1' minSize='-1' maxSize='-1' groupType='1' repHandlerStruct='' visible='true' inheritsFrom='' V281='13' V1='4' name='E2BPPARNR000' description='Communications Fields: SD Document Partner: WWW'>
          <delimTerminator>\n</delimTerminator>
        </savedOrigCopyAtInheritsFrom>
        <delimTerminator>\n</delimTerminator>
      </child>
      <child t='167' id='43' V167='21' inheritsFromIncarnation='49' inheritsFromTimestamp='0x16d16668bb3' inheritsInThisStruct='true' V283='2' occurMaxTimes='999999999' minSize='-1' maxSize='-1' inheritsFromCopyRule='28' groupType='1' repHandlerStruct='' visible='true' inheritsFrom='Structures/Segments/E2BPSCHDL001.xml' V281='13' V1='4' name='E2BPSCHDL001' description='Communication Fields for Maintaining SD Doc. Schedule Lines' checksumValid='true' checksum='s7B77JXrIWjKY65GhztQ8zx6Qk0='>
        <structNode t='150' idref='1'/>
        <savedDerivedCopy t='167' id='44' V167='21' needInheritInit='true' inheritsInThisStruct='true' V283='2' occurMaxTimes='1' minSize='-1' maxSize='-1' dataType='2' repHandlerStruct='' visible='true' inheritsFrom='Structures/Segments/E2BPSCHDL001.xml' V281='13' V1='4' name='E2BPSCHDL001'>
        </savedDerivedCopy>
        <savedOrigCopyAtInheritsFrom t='167' id='45' V167='21' V283='2' occurMaxTimes='1' minSize='-1' maxSize='-1' groupType='1' repHandlerStruct='' visible='true' inheritsFrom='' V281='13' V1='4' name='E2BPSCHDL001' description='Communication Fields for Maintaining SD Doc. Schedule Lines'>
          <delimTerminator>\n</delimTerminator>
        </savedOrigCopyAtInheritsFrom>
        <delimTerminator>\n</delimTerminator>
      </child>
      <child t='167' id='46' V167='21' inheritsFromIncarnation='55' inheritsFromTimestamp='0x16d16668bb3' inheritsInThisStruct='true' V283='2' occurMaxTimes='999999999' minSize='-1' maxSize='-1' inheritsFromCopyRule='28' groupType='1' repHandlerStruct='' visible='true' inheritsFrom='Structures/Segments/E2BPSCHDLX001.xml' V281='13' V1='4' name='E2BPSCHDLX001' description='Checkbox List for Maintaining SD Document Schedule Line' checksumValid='true' checksum='8nsnC0keEpLiegp7pwF28B95en4='>
        <structNode t='150' idref='1'/>
        <savedDerivedCopy t='167' id='47' V167='21' needInheritInit='true' inheritsInThisStruct='true' V283='2' occurMaxTimes='1' minSize='-1' maxSize='-1' dataType='2' repHandlerStruct='' visible='true' inheritsFrom='Structures/Segments/E2BPSCHDLX001.xml' V281='13' V1='4' name='E2BPSCHDLX001'>
        </savedDerivedCopy>
        <savedOrigCopyAtInheritsFrom t='167' id='48' V167='21' V283='2' occurMaxTimes='1' minSize='-1' maxSize='-1' groupType='1' repHandlerStruct='' visible='true' inheritsFrom='' V281='13' V1='4' name='E2BPSCHDLX001' description='Checkbox List for Maintaining SD Document Schedule Line'>
          <delimTerminator>\n</delimTerminator>
        </savedOrigCopyAtInheritsFrom>
        <delimTerminator>\n</delimTerminator>
      </child>
      <child t='167' id='49' V167='21' inheritsFromIncarnation='216' inheritsFromTimestamp='0x16d16668bb3' inheritsInThisStruct='true' V283='2' occurMaxTimes='999999999' minSize='-1' maxSize='-1' inheritsFromCopyRule='28' groupType='1' repHandlerStruct='' visible='true' inheritsFrom='Structures/Segments/E2BPCOND002.xml' V281='13' V1='4' name='E2BPCOND002' description='Communication Fields for Maintaining Conditions in the Order' checksumValid='true' checksum='oM70aSx6kUMqkxgYLDcy9D0aCvc='>
        <structNode t='150' idref='1'/>
        <savedDerivedCopy t='167' id='50' V167='21' needInheritInit='true' inheritsInThisStruct='true' V283='2' occurMaxTimes='1' minSize='-1' maxSize='-1' dataType='2' repHandlerStruct='' visible='true' inheritsFrom='Structures/Segments/E2BPCOND002.xml' V281='13' V1='4' name='E2BPCOND002'>
        </savedDerivedCopy>
        <savedOrigCopyAtInheritsFrom t='167' id='51' V167='21' V283='2' occurMaxTimes='1' minSize='-1' maxSize='-1' groupType='1' repHandlerStruct='' visible='true' inheritsFrom='' V281='13' V1='4' name='E2BPCOND002' description='Communication Fields for Maintaining Conditions in the Order'>
          <delimTerminator>\n</delimTerminator>
        </savedOrigCopyAtInheritsFrom>
        <delimTerminator>\n</delimTerminator>
      </child>
      <child t='167' id='52' V167='21' inheritsFromIncarnation='28' inheritsFromTimestamp='0x16d16668bb3' inheritsInThisStruct='true' V283='2' occurMaxTimes='999999999' minSize='-1' maxSize='-1' inheritsFromCopyRule='28' groupType='1' repHandlerStruct='' visible='true' inheritsFrom='Structures/Segments/E2BPCONDX000.xml' V281='13' V1='4' name='E2BPCONDX000' description='Communication Fields for Maintaining Conditions in the Order' checksumValid='true' checksum='jnNSKgpleSWMb6YZs/nls28boJg='>
        <structNode t='150' idref='1'/>
        <savedDerivedCopy t='167' id='53' V167='21' needInheritInit='true' inheritsInThisStruct='true' V283='2' occurMaxTimes='1' minSize='-1' maxSize='-1' dataType='2' repHandlerStruct='' visible='true' inheritsFrom='Structures/Segments/E2BPCONDX000.xml' V281='13' V1='4' name='E2BPCONDX000'>
        </savedDerivedCopy>
        <savedOrigCopyAtInheritsFrom t='167' id='54' V167='21' V283='2' occurMaxTimes='1' minSize='-1' maxSize='-1' groupType='1' repHandlerStruct='' visible='true' inheritsFrom='' V281='13' V1='4' name='E2BPCONDX000' description='Communication Fields for Maintaining Conditions in the Order'>
          <delimTerminator>\n</delimTerminator>
        </savedOrigCopyAtInheritsFrom>
        <delimTerminator>\n</delimTerminator>
      </child>
      <child t='167' id='55' V167='21' inheritsFromIncarnation='30' inheritsFromTimestamp='0x16d16668bb3' inheritsInThisStruct='true' V283='2' occurMaxTimes='999999999' minSize='-1' maxSize='-1' inheritsFromCopyRule='28' groupType='1' repHandlerStruct='' visible='true' inheritsFrom='Structures/Segments/E2BPCUCFG000.xml' V281='13' V1='4' name='E2BPCUCFG000' description='CU: Configuration Data' checksumValid='true' checksum='0FCAGQW3TT/xo7BqpKe7kZ8PFtQ='>
        <structNode t='150' idref='1'/>
        <savedDerivedCopy t='167' id='56' V167='21' needInheritInit='true' inheritsInThisStruct='true' V283='2' occurMaxTimes='1' minSize='-1' maxSize='-1' dataType='2' repHandlerStruct='' visible='true' inheritsFrom='Structures/Segments/E2BPCUCFG000.xml' V281='13' V1='4' name='E2BPCUCFG000'>
        </savedDerivedCopy>
        <savedOrigCopyAtInheritsFrom t='167' id='57' V167='21' V283='2' occurMaxTimes='1' minSize='-1' maxSize='-1' groupType='1' repHandlerStruct='' visible='true' inheritsFrom='' V281='13' V1='4' name='E2BPCUCFG000' description='CU: Configuration Data'>
          <delimTerminator>\n</delimTerminator>
        </savedOrigCopyAtInheritsFrom>
        <delimTerminator>\n</delimTerminator>
      </child>
      <child t='167' id='58' V167='21' inheritsFromIncarnation='30' inheritsFromTimestamp='0x16d16668bb3' inheritsInThisStruct='true' V283='2' occurMaxTimes='999999999' minSize='-1' maxSize='-1' inheritsFromCopyRule='28' groupType='1' repHandlerStruct='' visible='true' inheritsFrom='Structures/Segments/E2BPCUINS000.xml' V281='13' V1='4' name='E2BPCUINS000' description='Instances of Several Configurations' checksumValid='true' checksum='IA9ERsCVzwUkgBDAzBNFMOKt6E0='>
        <structNode t='150' idref='1'/>
        <savedDerivedCopy t='167' id='59' V167='21' needInheritInit='true' inheritsInThisStruct='true' V283='2' occurMaxTimes='1' minSize='-1' maxSize='-1' dataType='2' repHandlerStruct='' visible='true' inheritsFrom='Structures/Segments/E2BPCUINS000.xml' V281='13' V1='4' name='E2BPCUINS000'>
        </savedDerivedCopy>
        <savedOrigCopyAtInheritsFrom t='167' id='60' V167='21' V283='2' occurMaxTimes='1' minSize='-1' maxSize='-1' groupType='1' repHandlerStruct='' visible='true' inheritsFrom='' V281='13' V1='4' name='E2BPCUINS000' description='Instances of Several Configurations'>
          <delimTerminator>\n</delimTerminator>
        </savedOrigCopyAtInheritsFrom>
        <delimTerminator>\n</delimTerminator>
      </child>
      <child t='167' id='61' V167='21' inheritsFromIncarnation='24' inheritsFromTimestamp='0x16d16668bb3' inheritsInThisStruct='true' V283='2' occurMaxTimes='999999999' minSize='-1' maxSize='-1' inheritsFromCopyRule='28' groupType='1' repHandlerStruct='' visible='true' inheritsFrom='Structures/Segments/E2BPCUPRT000.xml' V281='13' V1='4' name='E2BPCUPRT000' description='Part_of Entries of Several Configurations' checksumValid='true' checksum='wj0MRFlt4+T7fXm7rG9vuPh5WMY='>
        <structNode t='150' idref='1'/>
        <savedDerivedCopy t='167' id='62' V167='21' needInheritInit='true' inheritsInThisStruct='true' V283='2' occurMaxTimes='1' minSize='-1' maxSize='-1' dataType='2' repHandlerStruct='' visible='true' inheritsFrom='Structures/Segments/E2BPCUPRT000.xml' V281='13' V1='4' name='E2BPCUPRT000'>
        </savedDerivedCopy>
        <savedOrigCopyAtInheritsFrom t='167' id='63' V167='21' V283='2' occurMaxTimes='1' minSize='-1' maxSize='-1' groupType='1' repHandlerStruct='' visible='true' inheritsFrom='' V281='13' V1='4' name='E2BPCUPRT000' description='Part_of Entries of Several Configurations'>
          <delimTerminator>\n</delimTerminator>
        </savedOrigCopyAtInheritsFrom>
        <delimTerminator>\n</delimTerminator>
      </child>
      <child t='167' id='64' V167='21' inheritsFromIncarnation='33' inheritsFromTimestamp='0x16d16668bb3' inheritsInThisStruct='true' V283='2' occurMaxTimes='999999999' minSize='-1' maxSize='-1' inheritsFromCopyRule='28' groupType='1' repHandlerStruct='' visible='true' inheritsFrom='Structures/Segments/E2BPCUVAL000.xml' V281='13' V1='4' name='E2BPCUVAL000' description='Characteristic Value Assignments for Several Configurations' checksumValid='true' checksum='yL61sR27DMtPBz6m8vnkhOsk2Bo='>
        <structNode t='150' idref='1'/>
        <savedDerivedCopy t='167' id='65' V167='21' needInheritInit='true' inheritsInThisStruct='true' V283='2' occurMaxTimes='1' minSize='-1' maxSize='-1' dataType='2' repHandlerStruct='' visible='true' inheritsFrom='Structures/Segments/E2BPCUVAL000.xml' V281='13' V1='4' name='E2BPCUVAL000'>
        </savedDerivedCopy>
        <savedOrigCopyAtInheritsFrom t='167' id='66' V167='21' V283='2' occurMaxTimes='1' minSize='-1' maxSize='-1' groupType='1' repHandlerStruct='' visible='true' inheritsFrom='' V281='13' V1='4' name='E2BPCUVAL000' description='Characteristic Value Assignments for Several Configurations'>
          <delimTerminator>\n</delimTerminator>
        </savedOrigCopyAtInheritsFrom>
        <delimTerminator>\n</delimTerminator>
      </child>
      <child t='167' id='67' V167='21' inheritsFromIncarnation='16' inheritsFromTimestamp='0x16d16668bb3' inheritsInThisStruct='true' V283='2' occurMaxTimes='999999999' minSize='-1' maxSize='-1' inheritsFromCopyRule='28' groupType='1' repHandlerStruct='' visible='true' inheritsFrom='Structures/Segments/E2BPCUBLB000.xml' V281='13' V1='4' name='E2BPCUBLB000' description='BLOB Internal Configuration Data (SCE)' checksumValid='true' checksum='WT2dNFvo/D97pgXh5+jQeXOrsWg='>
        <structNode t='150' idref='1'/>
        <savedDerivedCopy t='167' id='68' V167='21' needInheritInit='true' inheritsInThisStruct='true' V283='2' occurMaxTimes='1' minSize='-1' maxSize='-1' dataType='2' repHandlerStruct='' visible='true' inheritsFrom='Structures/Segments/E2BPCUBLB000.xml' V281='13' V1='4' name='E2BPCUBLB000'>
        </savedDerivedCopy>
        <savedOrigCopyAtInheritsFrom t='167' id='69' V167='21' V283='2' occurMaxTimes='1' minSize='-1' maxSize='-1' groupType='1' repHandlerStruct='' visible='true' inheritsFrom='' V281='13' V1='4' name='E2BPCUBLB000' description='BLOB Internal Configuration Data (SCE)'>
          <delimTerminator>\n</delimTerminator>
        </savedOrigCopyAtInheritsFrom>
        <delimTerminator>\n</delimTerminator>
      </child>
      <child t='167' id='70' V167='21' inheritsFromIncarnation='18' inheritsFromTimestamp='0x16d16668bb3' inheritsInThisStruct='true' V283='2' occurMaxTimes='999999999' minSize='-1' maxSize='-1' inheritsFromCopyRule='28' groupType='1' repHandlerStruct='' visible='true' inheritsFrom='Structures/Segments/E2BPCUVK000.xml' V281='13' V1='4' name='E2BPCUVK000' description='Variant Condition Keys in Configurations' checksumValid='true' checksum='ftM4mFNFXeep0BxYB1GzbmI2uxA='>
        <structNode t='150' idref='1'/>
        <savedDerivedCopy t='167' id='71' V167='21' needInheritInit='true' inheritsInThisStruct='true' V283='2' occurMaxTimes='1' minSize='-1' maxSize='-1' dataType='2' repHandlerStruct='' visible='true' inheritsFrom='Structures/Segments/E2BPCUVK000.xml' V281='13' V1='4' name='E2BPCUVK000'>
        </savedDerivedCopy>
        <savedOrigCopyAtInheritsFrom t='167' id='72' V167='21' V283='2' occurMaxTimes='1' minSize='-1' maxSize='-1' groupType='1' repHandlerStruct='' visible='true' inheritsFrom='' V281='13' V1='4' name='E2BPCUVK000' description='Variant Condition Keys in Configurations'>
          <delimTerminator>\n</delimTerminator>
        </savedOrigCopyAtInheritsFrom>
        <delimTerminator>\n</delimTerminator>
      </child>
      <child t='167' id='73' V167='21' inheritsFromIncarnation='17' inheritsFromTimestamp='0x16d16668bb3' inheritsInThisStruct='true' V283='2' occurMaxTimes='999999999' minSize='-1' maxSize='-1' inheritsFromCopyRule='28' groupType='1' repHandlerStruct='' visible='true' inheritsFrom='Structures/Segments/E2BPCUREF000.xml' V281='13' V1='4' name='E2BPCUREF000' description='CU: Reference Order Item / Instance in Configuration' checksumValid='true' checksum='UpOxcqqc6tcRhzhSGuKsa1zIQDY='>
        <structNode t='150' idref='1'/>
        <savedDerivedCopy t='167' id='74' V167='21' needInheritInit='true' inheritsInThisStruct='true' V283='2' occurMaxTimes='1' minSize='-1' maxSize='-1' dataType='2' repHandlerStruct='' visible='true' inheritsFrom='Structures/Segments/E2BPCUREF000.xml' V281='13' V1='4' name='E2BPCUREF000'>
        </savedDerivedCopy>
        <savedOrigCopyAtInheritsFrom t='167' id='75' V167='21' V283='2' occurMaxTimes='1' minSize='-1' maxSize='-1' groupType='1' repHandlerStruct='' visible='true' inheritsFrom='' V281='13' V1='4' name='E2BPCUREF000' description='CU: Reference Order Item / Instance in Configuration'>
          <delimTerminator>\n</delimTerminator>
        </savedOrigCopyAtInheritsFrom>
        <delimTerminator>\n</delimTerminator>
      </child>
      <child t='167' id='76' V167='21' inheritsFromIncarnation='72' inheritsFromTimestamp='0x16d16668bb3' inheritsInThisStruct='true' V283='2' occurMaxTimes='999999999' minSize='-1' maxSize='-1' inheritsFromCopyRule='28' groupType='1' repHandlerStruct='' visible='true' inheritsFrom='Structures/Segments/E2BPCCARD005.xml' V281='13' V1='4' name='E2BPCCARD005' description='Communication Table: Means of Payment Order/Billing Document' checksumValid='true' checksum='u10VPniWsC6tS/FgPpDAgyDiPUY='>
        <structNode t='150' idref='1'/>
        <savedDerivedCopy t='167' id='77' V167='21' needInheritInit='true' inheritsInThisStruct='true' V283='2' occurMaxTimes='1' minSize='-1' maxSize='-1' dataType='2' repHandlerStruct='' visible='true' inheritsFrom='Structures/Segments/E2BPCCARD005.xml' V281='13' V1='4' name='E2BPCCARD005'>
        </savedDerivedCopy>
        <savedOrigCopyAtInheritsFrom t='167' id='78' V167='21' V283='2' occurMaxTimes='1' minSize='-1' maxSize='-1' groupType='1' repHandlerStruct='' visible='true' inheritsFrom='' V281='13' V1='4' name='E2BPCCARD005' description='Communication Table: Means of Payment Order/Billing Document'>
          <delimTerminator>\n</delimTerminator>
        </savedOrigCopyAtInheritsFrom>
        <delimTerminator>\n</delimTerminator>
      </child>
      <child t='167' id='79' V167='21' inheritsFromIncarnation='28' inheritsFromTimestamp='0x16d16668bb3' inheritsInThisStruct='true' V283='2' occurMaxTimes='999999999' minSize='-1' maxSize='-1' inheritsFromCopyRule='28' groupType='1' repHandlerStruct='' visible='true' inheritsFrom='Structures/Segments/E2BPSDTEXT000.xml' V281='13' V1='4' name='E2BPSDTEXT000' description='Communication Fields: SD Texts' checksumValid='true' checksum='GywKatCnacdnkMi1DXfzG7Hzk/E='>
        <structNode t='150' idref='1'/>
        <savedDerivedCopy t='167' id='80' V167='21' needInheritInit='true' inheritsInThisStruct='true' V283='2' occurMaxTimes='1' minSize='-1' maxSize='-1' dataType='2' repHandlerStruct='' visible='true' inheritsFrom='Structures/Segments/E2BPSDTEXT000.xml' V281='13' V1='4' name='E2BPSDTEXT000'>
        </savedDerivedCopy>
        <savedOrigCopyAtInheritsFrom t='167' id='81' V167='21' V283='2' occurMaxTimes='1' minSize='-1' maxSize='-1' groupType='1' repHandlerStruct='' visible='true' inheritsFrom='' V281='13' V1='4' name='E2BPSDTEXT000' description='Communication Fields: SD Texts'>
          <delimTerminator>\n</delimTerminator>
        </savedOrigCopyAtInheritsFrom>
        <delimTerminator>\n</delimTerminator>
      </child>
      <child t='167' id='82' V167='21' inheritsFromIncarnation='38' inheritsFromTimestamp='0x16d16668bb3' inheritsInThisStruct='true' V283='2' occurMaxTimes='999999999' minSize='-1' maxSize='-1' inheritsFromCopyRule='28' groupType='1' repHandlerStruct='' visible='true' inheritsFrom='Structures/Segments/E2BPSDKEY001.xml' V281='13' V1='4' name='E2BPSDKEY001' description='Key in Sales and Distribution Document' checksumValid='true' checksum='ZI2BqqTqcEnXMGbvh4kS+4Neh0I='>
        <structNode t='150' idref='1'/>
        <savedDerivedCopy t='167' id='83' V167='21' needInheritInit='true' inheritsInThisStruct='true' V283='2' occurMaxTimes='1' minSize='-1' maxSize='-1' dataType='2' repHandlerStruct='' visible='true' inheritsFrom='Structures/Segments/E2BPSDKEY001.xml' V281='13' V1='4' name='E2BPSDKEY001'>
        </savedDerivedCopy>
        <savedOrigCopyAtInheritsFrom t='167' id='84' V167='21' V283='2' occurMaxTimes='1' minSize='-1' maxSize='-1' groupType='1' repHandlerStruct='' visible='true' inheritsFrom='' V281='13' V1='4' name='E2BPSDKEY001' description='Key in Sales and Distribution Document'>
          <delimTerminator>\n</delimTerminator>
        </savedOrigCopyAtInheritsFrom>
        <delimTerminator>\n</delimTerminator>
      </child>
      <child t='167' id='85' V167='21' inheritsFromIncarnation='19' inheritsFromTimestamp='0x16d16668bb3' inheritsInThisStruct='true' V283='2' occurMaxTimes='999999999' minSize='-1' maxSize='-1' inheritsFromCopyRule='28' groupType='1' repHandlerStruct='' visible='true' inheritsFrom='Structures/Segments/E2BPPAREX000.xml' V281='13' V1='4' name='E2BPPAREX000' description='Ref. Structure for BAPI Parameter EXTENSIONIN/EXTENSIONOUT' checksumValid='true' checksum='8439LmqW5lVNG0wt9PMZ+8T82z4='>
        <structNode t='150' idref='1'/>
        <savedDerivedCopy t='167' id='86' V167='21' needInheritInit='true' inheritsInThisStruct='true' V283='2' occurMaxTimes='1' minSize='-1' maxSize='-1' dataType='2' repHandlerStruct='' visible='true' inheritsFrom='Structures/Segments/E2BPPAREX000.xml' V281='13' V1='4' name='E2BPPAREX000'>
        </savedDerivedCopy>
        <savedOrigCopyAtInheritsFrom t='167' id='87' V167='21' V283='2' occurMaxTimes='1' minSize='-1' maxSize='-1' groupType='1' repHandlerStruct='' visible='true' inheritsFrom='' V281='13' V1='4' name='E2BPPAREX000' description='Ref. Structure for BAPI Parameter EXTENSIONIN/EXTENSIONOUT'>
          <delimTerminator>\n</delimTerminator>
        </savedOrigCopyAtInheritsFrom>
        <delimTerminator>\n</delimTerminator>
      </child>
      <child t='167' id='88' V167='21' V283='2' occurMaxTimes='999999999' minSize='-1' maxSize='-1' groupType='1' repHandlerStruct='' visible='true' inheritsFrom='' V281='13' V1='4' name='Loop-E2BPADR1000' description='BAPI Reference Structure for Addresses (Org./Company)'>
        <structNode t='150' idref='1'/>
        <child t='167' id='89' V167='21' inheritsFromIncarnation='61' inheritsFromTimestamp='0x16d16668bb3' inheritsInThisStruct='true' V283='2' occurMinTimes='1' occurMaxTimes='1' minSize='-1' maxSize='-1' inheritsFromCopyRule='28' groupType='1' repHandlerStruct='' visible='true' inheritsFrom='Structures/Segments/E2BPADR1000.xml' V281='13' V1='4' name='E2BPADR1000' description='BAPI Reference Structure for Addresses (Org./Company)' checksumValid='true' checksum='Irnx9IG4igPuiJKo1v7sgy/Dp1Q='>
          <structNode t='150' idref='1'/>
          <savedDerivedCopy t='167' id='90' V167='21' needInheritInit='true' inheritsInThisStruct='true' V283='2' occurMaxTimes='1' minSize='-1' maxSize='-1' dataType='2' repHandlerStruct='' visible='true' inheritsFrom='Structures/Segments/E2BPADR1000.xml' V281='13' V1='4' name='E2BPADR1000'>
          </savedDerivedCopy>
          <savedOrigCopyAtInheritsFrom t='167' id='91' V167='21' V283='2' occurMaxTimes='1' minSize='-1' maxSize='-1' groupType='1' repHandlerStruct='' visible='true' inheritsFrom='' V281='13' V1='4' name='E2BPADR1000' description='BAPI Reference Structure for Addresses (Org./Company)'>
            <delimTerminator>\n</delimTerminator>
          </savedOrigCopyAtInheritsFrom>
          <delimTerminator>\n</delimTerminator>
        </child>
        <child t='167' id='92' V167='21' inheritsFromIncarnation='56' inheritsFromTimestamp='0x16d16668bb3' inheritsInThisStruct='true' V283='2' occurMaxTimes='1' minSize='-1' maxSize='-1' inheritsFromCopyRule='28' groupType='1' repHandlerStruct='' visible='true' inheritsFrom='Structures/Segments/E2BPADR11005.xml' V281='13' V1='4' name='E2BPADR11005' description='BAPI Reference Structure for Addresses (Org./Company)' checksumValid='true' checksum='pbTjhpslmXk0Gsjcq3fX7PQDEbA='>
          <structNode t='150' idref='1'/>
          <savedDerivedCopy t='167' id='93' V167='21' needInheritInit='true' inheritsInThisStruct='true' V283='2' occurMaxTimes='1' minSize='-1' maxSize='-1' dataType='2' repHandlerStruct='' visible='true' inheritsFrom='Structures/Segments/E2BPADR11005.xml' V281='13' V1='4' name='E2BPADR11005'>
          </savedDerivedCopy>
          <savedOrigCopyAtInheritsFrom t='167' id='94' V167='21' V283='2' occurMaxTimes='1' minSize='-1' maxSize='-1' groupType='1' repHandlerStruct='' visible='true' inheritsFrom='' V281='13' V1='4' name='E2BPADR11005' description='BAPI Reference Structure for Addresses (Org./Company)'>
            <delimTerminator>\n</delimTerminator>
          </savedOrigCopyAtInheritsFrom>
          <delimTerminator>\n</delimTerminator>
        </child>
      </child>
      <child t='167' id='95' V167='21' inheritsFromIncarnation='16' inheritsFromTimestamp='0x16d16668bb3' inheritsInThisStruct='true' V283='2' occurMaxTimes='999999' minSize='-1' maxSize='-1' inheritsFromCopyRule='28' groupType='1' repHandlerStruct='' visible='true' inheritsFrom='Structures/Segments/E2IDOCENHANCEMENT000.xml' V281='13' V1='4' name='E2IDOCENHANCEMENT000' description='Segment for Dynamic Enhancement of IDoc Types' checksumValid='true' checksum='/4Gzf3uzJqMIxr5E4q9GT5LitFc='>
        <structNode t='150' idref='1'/>
        <savedDerivedCopy t='167' id='96' V167='21' needInheritInit='true' inheritsInThisStruct='true' V283='2' occurMaxTimes='1' minSize='-1' maxSize='-1' dataType='2' repHandlerStruct='' visible='true' inheritsFrom='Structures/Segments/E2IDOCENHANCEMENT000.xml' V281='13' V1='4' name='E2IDOCENHANCEMENT000'>
        </savedDerivedCopy>
        <savedOrigCopyAtInheritsFrom t='167' id='97' V167='21' V283='2' occurMaxTimes='1' minSize='-1' maxSize='-1' groupType='1' repHandlerStruct='' visible='true' inheritsFrom='' V281='13' V1='4' name='E2IDOCENHANCEMENT000' description='Segment for Dynamic Enhancement of IDoc Types'>
          <delimTerminator>\n</delimTerminator>
        </savedOrigCopyAtInheritsFrom>
        <delimTerminator>\n</delimTerminator>
      </child>
    </child>
  </rootElem>
  <defaultRep t='181' id='98' V181='1' V170='10' V704='1' idoctyp='SALESORDER_CREATEFROMDAT204' V690='1' encoding='UTF-8' ignoreExcluded='true' fixInvalidCharacters='true' V1='4' name='IDocs'>
  </defaultRep>
  <child t='162' id='99' V1='4' name='Representations'>
    <child t='181' idref='98'/>
    <child t='172' id='100' V172='6' autoFixNamespaceMismatch='true' V170='10' V692='1' V690='1' ignoreExcluded='true' fixInvalidCharacters='true' V1='4' name='XML'>
    </child>
  </child>
  <child t='165' id='101' V1='4' name='Document Bindings'>
  </child>
</root>
